Workbook

Sheet Сводка по сотрудникам
A1: Итоговое совещание Энергомикс, Коломна, 28–30.10.2026 — стоимость проезда на 1 человека
A2: Цены на 28.09.2026. «Эконом» — самые дешёвые билеты (в т. ч. ранние вылеты, ночные рейсы и поезда). «Удобный» — без подъёма среди ночи и без ночи в дороге: вылет не раньше ~09:00, приезд в Коломну до 23:00, обратно 31.10 днём после ночи в гостинице. Детали — лист «Маршруты».
A4: № | B4: ФИО | C4: Должность | D4: Город | E4: Способ | F4: ЭКОНОМ: туда, без багажа | G4: туда, с багажом | H4: обратно, без багажа | I4: обратно, с багажом | J4: трансферы | K4: доп. ночей | L4: ИТОГО эконом без багажа | M4: ИТОГО эконом с багажом | N4: УДОБНЫЙ: туда (с багажом) | O4: обратно (с багажом) | P4: трансферы | Q4: доп. ночей | R4: ИТОГО удобный | S4: В ПУТИ эконом (туда + обратно, дверь–дверь) | T4: В ПУТИ удобный (туда + обратно, дверь–дверь) | U4: Комментарий
A5: 1 | B5: Марченко В.Н. | C5: уточнить | D5: Омск | E5: Самолёт | F5: 7655 | G5: 10548 | H5: 9591 | I5: 12638 | J5: 3000 | K5: 0 | L5: =F5+H5+J5+K5*'Правила и допущения'!$B$3 | M5: =G5+I5+J5+K5*'Правила и допущения'!$B$3 | N5: 14270 | O5: 12639 | P5: 6500 | Q5: 2 | R5: =N5+O5+P5+Q5*'Правила и допущения'!$B$3 | S5: 20 ч 55 мин | T5: 20 ч 15 мин | U5: Удобный: вылет днём 27.10 + ночь; обратно дневных рейсов нет — вечер 31.10
A6: 2 | B6: Яруллин И.Р. | C6: уточнить | D6: Уфа | E6: Самолёт | F6: 6638 | G6: 9416 | H6: 8417 | I6: 11288 | J6: 1800 | K6: 0 | L6: =F6+H6+J6+K6*'Правила и допущения'!$B$3 | M6: =G6+I6+J6+K6*'Правила и допущения'!$B$3 | N6: 11268 | O6: 12118 | P6: 6000 | Q6: 1 | R6: =N6+O6+P6+Q6*'Правила и допущения'!$B$3 | S6: 18 ч 00 мин | T6: 15 ч 05 мин | U6: Эконом: вылет 07:00 и ночной обратно
A7: 3 | B7: Григорьев Д.С. | C7: Начальник склада | D7: Ревда | E7: Самолёт | F7: 7113 | G7: 10054 | H7: 10285 | I7: 13388 | J7: 5100 | K7: 0 | L7: =F7+H7+J7+K7*'Правила и допущения'!$B$3 | M7: =G7+I7+J7+K7*'Правила и допущения'!$B$3 | N7: 13395 | O7: 15996 | P7: 6000 | Q7: 1 | R7: =N7+O7+P7+Q7*'Правила и допущения'!$B$3 | S7: 19 ч 05 мин | T7: 16 ч 05 мин | U7: Вкл. такси Ревда—Кольцово
A8: 4 | B8: Воронков И.Н. | C8: Руководитель СФО | D8: Новосибирск | E8: Самолёт | F8: 7623 | G8: 10502 | H8: 8607 | I8: 11632 | J8: 2600 | K8: 1 | L8: =F8+H8+J8+K8*'Правила и допущения'!$B$3 | M8: =G8+I8+J8+K8*'Правила и допущения'!$B$3 | N8: 14236 | O8: 15333 | P8: 3400 | Q8: 1 | R8: =N8+O8+P8+Q8*'Правила и допущения'!$B$3 | S8: 21 ч 40 мин | T8: 21 ч 30 мин | U8: Удобный: днём в обе стороны
A9: 5 | B9: Макаров А.Г. | C9: уточнить | D9: Абакан | E9: Самолёт | F9: 19228 | G9: 25593 | H9: 21247 | I9: 25201 | J9: 2700 | K9: 1 | L9: =F9+H9+J9+K9*'Правила и допущения'!$B$3 | M9: =G9+I9+J9+K9*'Правила и допущения'!$B$3 | N9: 25201 | O9: 25201 | P9: 10000 | Q9: 1 | R9: =N9+O9+P9+Q9*'Правила и допущения'!$B$3 | S9: 20 ч 20 мин | T9: 21 ч 30 мин | U9: Обратно только ночной рейс (дневных нет)
A10: 6 | B10: Дёмин А.М. | C10: уточнить | D10: Красноярск | E10: Самолёт | F10: 10652 | G10: 14050 | H10: 9430 | I10: 12647 | J10: 3000 | K10: 1 | L10: =F10+H10+J10+K10*'Правила и допущения'!$B$3 | M10: =G10+I10+J10+K10*'Правила и допущения'!$B$3 | N10: 19270 | O10: 25343 | P10: 10000 | Q10: 1 | R10: =N10+O10+P10+Q10*'Правила и допущения'!$B$3 | S10: 22 ч 35 мин | T10: 22 ч 35 мин | U10: Удобный: днём в обе стороны
A11: 7 | B11: Иванова Е.В. | C11: уточнить | D11: Новокузнецк | E11: Самолёт | F11: 14784 | G11: 20644 | H11: 14784 | I11: 20644 | J11: 2400 | K11: 0 | L11: =F11+H11+J11+K11*'Правила и допущения'!$B$3 | M11: =G11+I11+J11+K11*'Правила и допущения'!$B$3 | N11: 20644 | O11: 18619 | P11: 8000 | Q11: 1 | R11: =N11+O11+P11+Q11*'Правила и допущения'!$B$3 | S11: 20 ч 25 мин | T11: 19 ч 35 мин | U11: Обратно дневных рейсов нет — вечер 31.10 после отдыха
A12: 8 | B12: Видяев А.А. | C12: уточнить | D12: Новосибирск | E12: Самолёт | F12: 7623 | G12: 10502 | H12: 8607 | I12: 11632 | J12: 2600 | K12: 1 | L12: =F12+H12+J12+K12*'Правила и допущения'!$B$3 | M12: =G12+I12+J12+K12*'Правила и допущения'!$B$3 | N12: 14236 | O12: 15333 | P12: 3400 | Q12: 1 | R12: =N12+O12+P12+Q12*'Правила и допущения'!$B$3 | S12: 21 ч 40 мин | T12: 21 ч 30 мин | U12: Удобный: днём в обе стороны
A13: 9 | B13: Малышев А.А. | C13: Начальник склада | D13: Новосибирск | E13: Самолёт | F13: 7623 | G13: 10502 | H13: 8607 | I13: 11632 | J13: 2600 | K13: 1 | L13: =F13+H13+J13+K13*'Правила и допущения'!$B$3 | M13: =G13+I13+J13+K13*'Правила и допущения'!$B$3 | N13: 14236 | O13: 15333 | P13: 3400 | Q13: 1 | R13: =N13+O13+P13+Q13*'Правила и допущения'!$B$3 | S13: 21 ч 40 мин | T13: 21 ч 30 мин | U13: Удобный: днём в обе стороны
A14: 10 | B14: Панкратова Е.С. | C14: уточнить | D14: Ижевск | E14: Самолёт | F14: 8158 | G14: 11683 | H14: 8158 | I14: 11683 | J14: 3000 | K14: 1 | L14: =F14+H14+J14+K14*'Правила и допущения'!$B$3 | M14: =G14+I14+J14+K14*'Правила и допущения'!$B$3 | N14: 11683 | O14: 11683 | P14: 6000 | Q14: 1 | R14: =N14+O14+P14+Q14*'Правила и допущения'!$B$3 | S14: 13 ч 45 мин | T14: 13 ч 45 мин | U14: Эконом = удобный
A15: 11 | B15: Асхадуллин А.М. | C15: уточнить | D15: Казань | E15: Самолёт / поезд | F15: 3265 | G15: 5995 | H15: 4270 | I15: 4270 | J15: 2400 | K15: 0 | L15: =F15+H15+J15+K15*'Правила и допущения'!$B$3 | M15: =G15+I15+J15+K15*'Правила и допущения'!$B$3 | N15: 7021 | O15: 7722 | P15: 6500 | Q15: 1 | R15: =N15+O15+P15+Q15*'Правила и допущения'!$B$3 | S15: 25 ч 10 мин | T15: 16 ч 15 мин | U15: Самолёт дешевле поезда; эконом обратно — ночной поезд
A16: 12 | B16: Егоров Р.Л. | C16: уточнить | D16: Набережные Челны | E16: Самолёт | F16: 4517 | G16: 7237 | H16: 5056 | I16: 7775 | J16: 4600 | K16: 1 | L16: =F16+H16+J16+K16*'Правила и допущения'!$B$3 | M16: =G16+I16+J16+K16*'Правила и допущения'!$B$3 | N16: 7237 | O16: 7775 | P16: 8500 | Q16: 1 | R16: =N16+O16+P16+Q16*'Правила и допущения'!$B$3 | S16: 15 ч 40 мин | T16: 15 ч 40 мин | U16: Эконом = удобный
A17: 13 | B17: Попов Д.М. | C17: уточнить | D17: Оренбург | E17: Самолёт | F17: 7050 | G17: 9636 | H17: 8429 | I17: 8429 | J17: 3000 | K17: 0 | L17: =F17+H17+J17+K17*'Правила и допущения'!$B$3 | M17: =G17+I17+J17+K17*'Правила и допущения'!$B$3 | N17: 9636 | O17: 15985 | P17: 6500 | Q17: 1 | R17: =N17+O17+P17+Q17*'Правила и допущения'!$B$3 | S17: 19 ч 25 мин | T17: 16 ч 25 мин | U17: Эконом обратно — ночной рейс 02:40
A18: 14 | B18: Ирышков Е.А. | C18: уточнить | D18: Пенза | E18: Авто | F18: ='Авто'!J2/2 | G18: ='Авто'!J2/2 | H18: ='Авто'!J2/2 | I18: ='Авто'!J2/2 | J18: 0 | K18: 0 | L18: =F18+H18+J18+K18*'Правила и допущения'!$B$3 | M18: =G18+I18+J18+K18*'Правила и допущения'!$B$3 | N18: ='Авто'!J2/2 | O18: ='Авто'!J2/2 | P18: 0 | Q18: 1 | R18: =N18+O18+P18+Q18*'Правила и допущения'!$B$3 | S18: 15 ч 00 мин | T18: 15 ч 00 мин | U18: Экипаж: Пенза. Удобный = обратно 31.10 утром + ночь
A19: 15 | B19: Симбирев И.В. | C19: Руководитель ПФО | D19: Саратов | E19: Поезд / самолёт | F19: 4013 | G19: 4013 | H19: 5012 | I19: 7630 | J19: 2400 | K19: 1 | L19: =F19+H19+J19+K19*'Правила и допущения'!$B$3 | M19: =G19+I19+J19+K19*'Правила и допущения'!$B$3 | N19: 8442 | O19: 7630 | P19: 4750 | Q19: 1 | R19: =N19+O19+P19+Q19*'Правила и допущения'!$B$3 | S19: 28 ч 30 мин | T19: 15 ч 05 мин | U19: Эконом: ночной поезд туда. Удобный: самолёт днём
A20: 16 | B20: Щеголев М.Г. | C20: уточнить | D20: Самара | E20: Поезд / самолёт | F20: 3594 | G20: 3594 | H20: 6905 | I20: 6905 | J20: 1800 | K20: 0 | L20: =F20+H20+J20+K20*'Правила и допущения'!$B$3 | M20: =G20+I20+J20+K20*'Правила и допущения'!$B$3 | N20: 7347 | O20: 8293 | P20: 6500 | Q20: 1 | R20: =N20+O20+P20+Q20*'Правила и допущения'!$B$3 | S20: 37 ч 25 мин | T20: 16 ч 20 мин | U20: Эконом: ночные поезда. Удобный: дневные рейсы
A21: 17 | B21: Ильин Д.С. | C21: уточнить | D21: Саранск | E21: Авто | F21: ='Авто'!J3/2 | G21: ='Авто'!J3/2 | H21: ='Авто'!J3/2 | I21: ='Авто'!J3/2 | J21: 0 | K21: 0 | L21: =F21+H21+J21+K21*'Правила и допущения'!$B$3 | M21: =G21+I21+J21+K21*'Правила и допущения'!$B$3 | N21: ='Авто'!J3/2 | O21: ='Авто'!J3/2 | P21: 0 | Q21: 1 | R21: =N21+O21+P21+Q21*'Правила и допущения'!$B$3 | S21: 14 ч 00 мин | T21: 14 ч 00 мин | U21: Экипаж: Саранск. Удобный = обратно 31.10 утром + ночь
A22: 18 | B22: Бобков А.А. | C22: уточнить | D22: Саратов | E22: Поезд / самолёт | F22: 4013 | G22: 4013 | H22: 5012 | I22: 7630 | J22: 2400 | K22: 1 | L22: =F22+H22+J22+K22*'Правила и допущения'!$B$3 | M22: =G22+I22+J22+K22*'Правила и допущения'!$B$3 | N22: 8442 | O22: 7630 | P22: 4750 | Q22: 1 | R22: =N22+O22+P22+Q22*'Правила и допущения'!$B$3 | S22: 28 ч 30 мин | T22: 15 ч 05 мин | U22: Эконом: ночной поезд туда. Удобный: самолёт днём
A23: 19 | B23: Самсонов С.А. | C23: уточнить | D23: Ульяновск | E23: Самолёт | F23: 4938 | G23: 7618 | H23: 5628 | I23: 8367 | J23: 1800 | K23: 1 | L23: =F23+H23+J23+K23*'Правила и допущения'!$B$3 | M23: =G23+I23+J23+K23*'Правила и допущения'!$B$3 | N23: 7618 | O23: 8367 | P23: 4500 | Q23: 1 | R23: =N23+O23+P23+Q23*'Правила и допущения'!$B$3 | S23: 14 ч 40 мин | T23: 14 ч 40 мин | U23: Эконом = удобный
A24: 20 | B24: Каратаев Д.В. | C24: уточнить | D24: Чебоксары | E24: Самолёт / поезд | F24: 4214 | G24: 6754 | H24: 3884 | I24: 3884 | J24: 3000 | K24: 0 | L24: =F24+H24+J24+K24*'Правила и допущения'!$B$3 | M24: =G24+I24+J24+K24*'Правила и допущения'!$B$3 | N24: 6754 | O24: 6754 | P24: 6500 | Q24: 1 | R24: =N24+O24+P24+Q24*'Правила и допущения'!$B$3 | S24: 24 ч 40 мин | T24: 14 ч 55 мин | U24: Туда самолёт днём; эконом обратно — ночной поезд
A25: 21 | B25: Рябов И.А. | C25: Начальник склада | D25: Ульяновск | E25: Самолёт | F25: 4938 | G25: 7618 | H25: 5628 | I25: 8367 | J25: 1800 | K25: 1 | L25: =F25+H25+J25+K25*'Правила и допущения'!$B$3 | M25: =G25+I25+J25+K25*'Правила и допущения'!$B$3 | N25: 7618 | O25: 8367 | P25: 4500 | Q25: 1 | R25: =N25+O25+P25+Q25*'Правила и допущения'!$B$3 | S25: 14 ч 40 мин | T25: 14 ч 40 мин | U25: Эконом = удобный
A26: 22 | B26: Федосеенко Т.А. | C26: уточнить | D26: Улан-Удэ | E26: Самолёт | F26: 16931 | G26: 21094 | H26: 21098 | I26: 28884 | J26: 2700 | K26: 0 | L26: =F26+H26+J26+K26*'Правила и допущения'!$B$3 | M26: =G26+I26+J26+K26*'Правила и допущения'!$B$3 | N26: 21094 | O26: 21094 | P26: 10000 | Q26: 1 | R26: =N26+O26+P26+Q26*'Правила и допущения'!$B$3 | S26: 23 ч 55 мин | T26: 24 ч 10 мин | U26: Обратно дневных рейсов нет — вечер 31.10, прилёт утром
A27: 23 | B27: Шевченко С.В. | C27: Межгород | D27: Иркутск | E27: Самолёт | F27: 12305 | G27: 15862 | H27: 12308 | I27: 15879 | J27: 1800 | K27: 1 | L27: =F27+H27+J27+K27*'Правила и допущения'!$B$3 | M27: =G27+I27+J27+K27*'Правила и допущения'!$B$3 | N27: 17607 | O27: 19332 | P27: 2200 | Q27: 1 | R27: =N27+O27+P27+Q27*'Правила и допущения'!$B$3 | S27: 22 ч 45 мин | T27: 23 ч 45 мин | U27: Группа 5 чел.: минивэн
A28: 24 | B28: Донской И.С. | C28: Оптовый отдел | D28: Иркутск | E28: Самолёт | F28: 12305 | G28: 15862 | H28: 12308 | I28: 15879 | J28: 1800 | K28: 1 | L28: =F28+H28+J28+K28*'Правила и допущения'!$B$3 | M28: =G28+I28+J28+K28*'Правила и допущения'!$B$3 | N28: 17607 | O28: 19332 | P28: 2200 | Q28: 1 | R28: =N28+O28+P28+Q28*'Правила и допущения'!$B$3 | S28: 22 ч 45 мин | T28: 23 ч 45 мин | U28: Группа 5 чел.: минивэн
A29: 25 | B29: Друсалевич В.В. | C29: уточнить | D29: Иркутск | E29: Самолёт | F29: 12305 | G29: 15862 | H29: 12308 | I29: 15879 | J29: 1800 | K29: 1 | L29: =F29+H29+J29+K29*'Правила и допущения'!$B$3 | M29: =G29+I29+J29+K29*'Правила и допущения'!$B$3 | N29: 17607 | O29: 19332 | P29: 2200 | Q29: 1 | R29: =N29+O29+P29+Q29*'Правила и допущения'!$B$3 | S29: 22 ч 45 мин | T29: 23 ч 45 мин | U29: Едет вместе с отцом (Друсалевич В.А.). Группа 5 чел.: минивэн
A30: 26 | B30: Бадмацыренов Т.Ц. | C30: уточнить | D30: Чита | E30: Самолёт | F30: 17671 | G30: 25050 | H30: 22835 | I30: 28993 | J30: 2400 | K30: 1 | L30: =F30+H30+J30+K30*'Правила и допущения'!$B$3 | M30: =G30+I30+J30+K30*'Правила и допущения'!$B$3 | N30: 28993 | O30: 28993 | P30: 6000 | Q30: 1 | R30: =N30+O30+P30+Q30*'Правила и допущения'!$B$3 | S30: 29 ч 10 мин | T30: 22 ч 35 мин | U30: Удобный: прямой рейс днём; обратно только вечерние рейсы
A31: 27 | B31: Петрова Т.А. | C31: уточнить | D31: Иркутск | E31: Самолёт | F31: 12305 | G31: 15862 | H31: 12308 | I31: 15879 | J31: 1800 | K31: 1 | L31: =F31+H31+J31+K31*'Правила и допущения'!$B$3 | M31: =G31+I31+J31+K31*'Правила и допущения'!$B$3 | N31: 17607 | O31: 19332 | P31: 2200 | Q31: 1 | R31: =N31+O31+P31+Q31*'Правила и допущения'!$B$3 | S31: 22 ч 45 мин | T31: 23 ч 45 мин | U31: Группа 5 чел.: минивэн
A32: 28 | B32: Летуновский В.М. | C32: Руководитель ЦЧР | D32: Воронеж | E32: Авто | F32: ='Авто'!J6/2 | G32: ='Авто'!J6/2 | H32: ='Авто'!J6/2 | I32: ='Авто'!J6/2 | J32: 0 | K32: 0 | L32: =F32+H32+J32+K32*'Правила и допущения'!$B$3 | M32: =G32+I32+J32+K32*'Правила и допущения'!$B$3 | N32: ='Авто'!J6/2 | O32: ='Авто'!J6/2 | P32: 0 | Q32: 1 | R32: =N32+O32+P32+Q32*'Правила и допущения'!$B$3 | S32: 11 ч 00 мин | T32: 11 ч 00 мин | U32: Экипаж: Воронеж (2 чел.). Удобный = обратно 31.10 утром + ночь
A33: 29 | B33: Иванищева А.В. | C33: Руководитель РЦ | D33: Липецк | E33: Авто | F33: ='Авто'!J5/2 | G33: ='Авто'!J5/2 | H33: ='Авто'!J5/2 | I33: ='Авто'!J5/2 | J33: 0 | K33: 0 | L33: =F33+H33+J33+K33*'Правила и допущения'!$B$3 | M33: =G33+I33+J33+K33*'Правила и допущения'!$B$3 | N33: ='Авто'!J5/2 | O33: ='Авто'!J5/2 | P33: 0 | Q33: 1 | R33: =N33+O33+P33+Q33*'Правила и допущения'!$B$3 | S33: 10 ч 00 мин | T33: 10 ч 00 мин | U33: Экипаж: Липецк (3 чел.). Удобный = обратно 31.10 утром + ночь
A34: 30 | B34: Майоров С.А. | C34: уточнить | D34: Астрахань | E34: Самолёт | F34: 7124 | G34: 9710 | H34: 7124 | I34: 9710 | J34: 3000 | K34: 1 | L34: =F34+H34+J34+K34*'Правила и допущения'!$B$3 | M34: =G34+I34+J34+K34*'Правила и допущения'!$B$3 | N34: 9710 | O34: 9710 | P34: 6500 | Q34: 1 | R34: =N34+O34+P34+Q34*'Правила и допущения'!$B$3 | S34: 17 ч 15 мин | T34: 17 ч 15 мин | U34: Эконом = удобный
A35: 31 | B35: Несмачный А.П. | C35: уточнить | D35: Белгород | E35: Поезд | F35: 2739 | G35: 2739 | H35: 3947 | I35: 3947 | J35: 1800 | K35: 0 | L35: =F35+H35+J35+K35*'Правила и допущения'!$B$3 | M35: =G35+I35+J35+K35*'Правила и допущения'!$B$3 | N35: 2739 | O35: 2674 | P35: 1800 | Q35: 1 | R35: =N35+O35+P35+Q35*'Правила и допущения'!$B$3 | S35: 31 ч 55 мин | T35: 22 ч 00 мин | U35: Туда Ласточка днём; эконом обратно — ночной поезд
A36: 32 | B36: Бондарев С.А. | C36: уточнить | D36: Брянск | E36: Авто | F36: ='Авто'!J7/2 | G36: ='Авто'!J7/2 | H36: ='Авто'!J7/2 | I36: ='Авто'!J7/2 | J36: 0 | K36: 0 | L36: =F36+H36+J36+K36*'Правила и допущения'!$B$3 | M36: =G36+I36+J36+K36*'Правила и допущения'!$B$3 | N36: ='Авто'!J7/2 | O36: ='Авто'!J7/2 | P36: 0 | Q36: 1 | R36: =N36+O36+P36+Q36*'Правила и допущения'!$B$3 | S36: 13 ч 00 мин | T36: 13 ч 00 мин | U36: Экипаж: Брянск + Орёл. Удобный = обратно 31.10 утром + ночь
A37: 33 | B37: Ситин В.А. | C37: уточнить | D37: Волгоград | E37: Самолёт | F37: 6406 | G37: 9061 | H37: 7155 | I37: 9893 | J37: 3000 | K37: 1 | L37: =F37+H37+J37+K37*'Правила и допущения'!$B$3 | M37: =G37+I37+J37+K37*'Правила и допущения'!$B$3 | N37: 9061 | O37: 9893 | P37: 6500 | Q37: 1 | R37: =N37+O37+P37+Q37*'Правила и допущения'!$B$3 | S37: 16 ч 50 мин | T37: 16 ч 50 мин | U37: Эконом = удобный
A38: 34 | B38: Штанько О.М. | C38: уточнить | D38: Воронеж | E38: Авто | F38: ='Авто'!J6/2 | G38: ='Авто'!J6/2 | H38: ='Авто'!J6/2 | I38: ='Авто'!J6/2 | J38: 0 | K38: 0 | L38: =F38+H38+J38+K38*'Правила и допущения'!$B$3 | M38: =G38+I38+J38+K38*'Правила и допущения'!$B$3 | N38: ='Авто'!J6/2 | O38: ='Авто'!J6/2 | P38: 0 | Q38: 1 | R38: =N38+O38+P38+Q38*'Правила и допущения'!$B$3 | S38: 11 ч 00 мин | T38: 11 ч 00 мин | U38: Экипаж: Воронеж (2 чел.). Удобный = обратно 31.10 утром + ночь
A39: 35 | B39: Кузнецов А.А. | C39: уточнить | D39: Липецк | E39: Авто | F39: ='Авто'!J5/2 | G39: ='Авто'!J5/2 | H39: ='Авто'!J5/2 | I39: ='Авто'!J5/2 | J39: 0 | K39: 0 | L39: =F39+H39+J39+K39*'Правила и допущения'!$B$3 | M39: =G39+I39+J39+K39*'Правила и допущения'!$B$3 | N39: ='Авто'!J5/2 | O39: ='Авто'!J5/2 | P39: 0 | Q39: 1 | R39: =N39+O39+P39+Q39*'Правила и допущения'!$B$3 | S39: 10 ч 00 мин | T39: 10 ч 00 мин | U39: Экипаж: Липецк (3 чел.). Удобный = обратно 31.10 утром + ночь
A40: 36 | B40: Мамонов С.В. | C40: уточнить | D40: Орёл | E40: Авто | F40: ='Авто'!J7/2 | G40: ='Авто'!J7/2 | H40: ='Авто'!J7/2 | I40: ='Авто'!J7/2 | J40: 0 | K40: 0 | L40: =F40+H40+J40+K40*'Правила и допущения'!$B$3 | M40: =G40+I40+J40+K40*'Правила и допущения'!$B$3 | N40: ='Авто'!J7/2 | O40: ='Авто'!J7/2 | P40: 0 | Q40: 1 | R40: =N40+O40+P40+Q40*'Правила и допущения'!$B$3 | S40: 13 ч 00 мин | T40: 13 ч 00 мин | U40: Экипаж: Брянск + Орёл. Удобный = обратно 31.10 утром + ночь
A41: 37 | B41: Козак С.С. | C41: уточнить | D41: Донецк | E41: Автобус / поезд через Ростов | F41: 3500 | G41: 3500 | H41: 4000 | I41: 4000 | J41: 1800 | K41: 1 | L41: =F41+H41+J41+K41*'Правила и допущения'!$B$3 | M41: =G41+I41+J41+K41*'Правила и допущения'!$B$3 | N41: 6793 | O41: 7132 | P41: 4800 | Q41: 0 | R41: =N41+O41+P41+Q41*'Правила и допущения'!$B$3 | S41: 51 ч 30 мин | T41: 59 ч 00 мин | U41: Ночь в дороге неизбежна; удобный — в купе. Вкл. Донецк—Ростов ~1 500 ₽ в каждую сторону
A42: 38 | B42: Горелкин Д.Е. | C42: уточнить | D42: Тамбов | E42: Авто | F42: ='Авто'!J4/2 | G42: ='Авто'!J4/2 | H42: ='Авто'!J4/2 | I42: ='Авто'!J4/2 | J42: 0 | K42: 0 | L42: =F42+H42+J42+K42*'Правила и допущения'!$B$3 | M42: =G42+I42+J42+K42*'Правила и допущения'!$B$3 | N42: ='Авто'!J4/2 | O42: ='Авто'!J4/2 | P42: 0 | Q42: 1 | R42: =N42+O42+P42+Q42*'Правила и допущения'!$B$3 | S42: 10 ч 00 мин | T42: 10 ч 00 мин | U42: Экипаж: Тамбов. Удобный = обратно 31.10 утром + ночь
A43: 39 | B43: Зайцев С.А. | C43: уточнить | D43: Липецк | E43: Авто | F43: ='Авто'!J5/2 | G43: ='Авто'!J5/2 | H43: ='Авто'!J5/2 | I43: ='Авто'!J5/2 | J43: 0 | K43: 0 | L43: =F43+H43+J43+K43*'Правила и допущения'!$B$3 | M43: =G43+I43+J43+K43*'Правила и допущения'!$B$3 | N43: ='Авто'!J5/2 | O43: ='Авто'!J5/2 | P43: 0 | Q43: 1 | R43: =N43+O43+P43+Q43*'Правила и допущения'!$B$3 | S43: 10 ч 00 мин | T43: 10 ч 00 мин | U43: Экипаж: Липецк (3 чел.). Удобный = обратно 31.10 утром + ночь
A44: 40 | B44: Друсалевич Владимир Анатольевич | C44: Директор | D44: Иркутск | E44: Самолёт | F44: 12305 | G44: 15862 | H44: 12308 | I44: 15879 | J44: 1800 | K44: 1 | L44: =F44+H44+J44+K44*'Правила и допущения'!$B$3 | M44: =G44+I44+J44+K44*'Правила и допущения'!$B$3 | N44: 17607 | O44: 19332 | P44: 2200 | Q44: 1 | R44: =N44+O44+P44+Q44*'Правила и допущения'!$B$3 | S44: 22 ч 45 мин | T44: 23 ч 45 мин | U44: Едет вместе с сыном (Друсалевич В.В.). Группа 5 чел.: минивэн
A45: 41 | B45: Колчин Андрей Ильич | C45: уточнить | D45: Москва | E45: Электричка / авто | F45: 490 | G45: 490 | H45: 490 | I45: 490 | J45: 800 | K45: 0 | L45: =F45+H45+J45+K45*'Правила и допущения'!$B$3 | M45: =G45+I45+J45+K45*'Правила и допущения'!$B$3 | N45: 750 | O45: 750 | P45: 0 | Q45: 0 | R45: =N45+O45+P45+Q45*'Правила и допущения'!$B$3 | S45: 6 ч 45 мин | T45: 4 ч 00 мин | U45: Удобный — своя машина
A46: 42 | B46: Мордвинов Сергей Анатольевич | C46: уточнить | D46: Москва | E46: Электричка / авто | F46: 490 | G46: 490 | H46: 490 | I46: 490 | J46: 800 | K46: 0 | L46: =F46+H46+J46+K46*'Правила и допущения'!$B$3 | M46: =G46+I46+J46+K46*'Правила и допущения'!$B$3 | N46: 750 | O46: 750 | P46: 0 | Q46: 0 | R46: =N46+O46+P46+Q46*'Правила и допущения'!$B$3 | S46: 6 ч 45 мин | T46: 4 ч 00 мин | U46: Удобный — своя машина
A47: 43 | B47: Бабкин Виктор Александрович | C47: уточнить | D47: Нижний Новгород | E47: Авто | F47: ='Авто'!J8/2 | G47: ='Авто'!J8/2 | H47: ='Авто'!J8/2 | I47: ='Авто'!J8/2 | J47: 0 | K47: 0 | L47: =F47+H47+J47+K47*'Правила и допущения'!$B$3 | M47: =G47+I47+J47+K47*'Правила и допущения'!$B$3 | N47: ='Авто'!J8/2 | O47: ='Авто'!J8/2 | P47: 0 | Q47: 1 | R47: =N47+O47+P47+Q47*'Правила и допущения'!$B$3 | S47: 12 ч 00 мин | T47: 12 ч 00 мин | U47: Экипаж: Н. Новгород + Владимир (3 чел.). Удобный = обратно 31.10 утром + ночь
A48: 44 | B48: Полин Денис Валериевич | C48: уточнить | D48: Рязань | E48: Электричка / авто | F48: 306 | G48: 306 | H48: 306 | I48: 306 | J48: 600 | K48: 0 | L48: =F48+H48+J48+K48*'Правила и допущения'!$B$3 | M48: =G48+I48+J48+K48*'Правила и допущения'!$B$3 | N48: 650 | O48: 650 | P48: 0 | Q48: 0 | R48: =N48+O48+P48+Q48*'Правила и допущения'!$B$3 | S48: 5 ч 00 мин | T48: 3 ч 00 мин | U48: Удобный — своя машина (~100 км)
A49: 45 | B49: Летягина Евгения Андреевна | C49: СПб (юг) | D49: Санкт-Петербург | E49: Поезд | F49: 1121 | G49: 1121 | H49: 2185 | I49: 2185 | J49: 1800 | K49: 0 | L49: =F49+H49+J49+K49*'Правила и допущения'!$B$3 | M49: =G49+I49+J49+K49*'Правила и допущения'!$B$3 | N49: 4424 | O49: 2130 | P49: 1800 | Q49: 1 | R49: =N49+O49+P49+Q49*'Правила и допущения'!$B$3 | S49: 22 ч 10 мин | T49: 16 ч 55 мин | U49: Удобный: Сапсан туда, Аврора днём обратно
A50: 46 | B50: Понамарёв Василий Васильевич | C50: Смоленск, В.Луки | D50: Смоленск | E50: Поезд | F50: 1832 | G50: 1832 | H50: 4022 | I50: 4022 | J50: 1800 | K50: 0 | L50: =F50+H50+J50+K50*'Правила и допущения'!$B$3 | M50: =G50+I50+J50+K50*'Правила и допущения'!$B$3 | N50: 1832 | O50: 2595 | P50: 1800 | Q50: 1 | R50: =N50+O50+P50+Q50*'Правила и допущения'!$B$3 | S50: 19 ч 55 мин | T50: 16 ч 50 мин | U50: Ласточка туда; удобный обратно — Ласточка днём 31.10
A51: 47 | B51: Пирогов Игорь Владимирович | C51: уточнить | D51: Тверь | E51: Поезд / авто | F51: 695 | G51: 695 | H51: 1000 | I51: 1000 | J51: 1800 | K51: 0 | L51: =F51+H51+J51+K51*'Правила и допущения'!$B$3 | M51: =G51+I51+J51+K51*'Правила и допущения'!$B$3 | N51: 1885 | O51: 1885 | P51: 0 | Q51: 0 | R51: =N51+O51+P51+Q51*'Правила и допущения'!$B$3 | S51: 12 ч 35 мин | T51: 8 ч 00 мин | U51: Удобный — своя машина
A52: 48 | B52: Смирнов Игорь Алексеевич | C52: Собственник | D52: Екатеринбург | E52: Самолёт | F52: 7811 | G52: 10789 | H52: 9104 | I52: 12205 | J52: 2000 | K52: 0 | L52: =F52+H52+J52+K52*'Правила и допущения'!$B$3 | M52: =G52+I52+J52+K52*'Правила и допущения'!$B$3 | N52: 11932 | O52: 15996 | P52: 2400 | Q52: 1 | R52: =N52+O52+P52+Q52*'Правила и допущения'!$B$3 | S52: 17 ч 45 мин | T52: 15 ч 50 мин | U52: Едет вместе с дочерью (Смирнова Ю.И.). 9 чел. одним рейсом (обычные билеты, без групповых скидок); минивэны
A53: 49 | B53: Догодаева Екатерина Николаевна | C53: уточнить | D53: Екатеринбург | E53: Самолёт | F53: 7811 | G53: 10789 | H53: 9104 | I53: 12205 | J53: 2000 | K53: 0 | L53: =F53+H53+J53+K53*'Правила и допущения'!$B$3 | M53: =G53+I53+J53+K53*'Правила и допущения'!$B$3 | N53: 11932 | O53: 15996 | P53: 2400 | Q53: 1 | R53: =N53+O53+P53+Q53*'Правила и допущения'!$B$3 | S53: 17 ч 45 мин | T53: 15 ч 50 мин | U53: 9 чел. одним рейсом (обычные билеты, без групповых скидок); минивэны
A54: 50 | B54: Дудник Светлана Васильевна | C54: уточнить | D54: Екатеринбург | E54: Самолёт | F54: 7811 | G54: 10789 | H54: 9104 | I54: 12205 | J54: 2000 | K54: 0 | L54: =F54+H54+J54+K54*'Правила и допущения'!$B$3 | M54: =G54+I54+J54+K54*'Правила и допущения'!$B$3 | N54: 11932 | O54: 15996 | P54: 2400 | Q54: 1 | R54: =N54+O54+P54+Q54*'Правила и допущения'!$B$3 | S54: 17 ч 45 мин | T54: 15 ч 50 мин | U54: 9 чел. одним рейсом (обычные билеты, без групповых скидок); минивэны
A55: 51 | B55: Девлешова Татьяна Владимировна | C55: уточнить | D55: Екатеринбург | E55: Самолёт | F55: 7811 | G55: 10789 | H55: 9104 | I55: 12205 | J55: 2000 | K55: 0 | L55: =F55+H55+J55+K55*'Правила и допущения'!$B$3 | M55: =G55+I55+J55+K55*'Правила и допущения'!$B$3 | N55: 11932 | O55: 15996 | P55: 2400 | Q55: 1 | R55: =N55+O55+P55+Q55*'Правила и допущения'!$B$3 | S55: 17 ч 45 мин | T55: 15 ч 50 мин | U55: 9 чел. одним рейсом (обычные билеты, без групповых скидок); минивэны
A56: 52 | B56: Володина Людмила Эдуардовна | C56: уточнить | D56: Екатеринбург | E56: Самолёт | F56: 7811 | G56: 10789 | H56: 9104 | I56: 12205 | J56: 2000 | K56: 0 | L56: =F56+H56+J56+K56*'Правила и допущения'!$B$3 | M56: =G56+I56+J56+K56*'Правила и допущения'!$B$3 | N56: 11932 | O56: 15996 | P56: 2400 | Q56: 1 | R56: =N56+O56+P56+Q56*'Правила и допущения'!$B$3 | S56: 17 ч 45 мин | T56: 15 ч 50 мин | U56: 9 чел. одним рейсом (обычные билеты, без групповых скидок); минивэны
A57: 53 | B57: Шакирзянова Надежда Александровна | C57: уточнить | D57: Екатеринбург | E57: Самолёт | F57: 7811 | G57: 10789 | H57: 9104 | I57: 12205 | J57: 2000 | K57: 0 | L57: =F57+H57+J57+K57*'Правила и допущения'!$B$3 | M57: =G57+I57+J57+K57*'Правила и допущения'!$B$3 | N57: 11932 | O57: 15996 | P57: 2400 | Q57: 1 | R57: =N57+O57+P57+Q57*'Правила и допущения'!$B$3 | S57: 17 ч 45 мин | T57: 15 ч 50 мин | U57: 9 чел. одним рейсом (обычные билеты, без групповых скидок); минивэны
A58: 54 | B58: Смирнова Юлия Игоревна | C58: уточнить | D58: Екатеринбург | E58: Самолёт | F58: 7811 | G58: 10789 | H58: 9104 | I58: 12205 | J58: 2000 | K58: 0 | L58: =F58+H58+J58+K58*'Правила и допущения'!$B$3 | M58: =G58+I58+J58+K58*'Правила и допущения'!$B$3 | N58: 11932 | O58: 15996 | P58: 2400 | Q58: 1 | R58: =N58+O58+P58+Q58*'Правила и допущения'!$B$3 | S58: 17 ч 45 мин | T58: 15 ч 50 мин | U58: Едет вместе с отцом (Смирнов И.А.). 9 чел. одним рейсом (обычные билеты, без групповых скидок); минивэны
A59: 55 | B59: Микушин Евгений Геннадьевич | C59: уточнить | D59: Екатеринбург | E59: Самолёт | F59: 7811 | G59: 10789 | H59: 9104 | I59: 12205 | J59: 2000 | K59: 0 | L59: =F59+H59+J59+K59*'Правила и допущения'!$B$3 | M59: =G59+I59+J59+K59*'Правила и допущения'!$B$3 | N59: 11932 | O59: 15996 | P59: 2400 | Q59: 1 | R59: =N59+O59+P59+Q59*'Правила и допущения'!$B$3 | S59: 17 ч 45 мин | T59: 15 ч 50 мин | U59: 9 чел. одним рейсом (обычные билеты, без групповых скидок); минивэны
... A61: 57 | B61: Мелентьев Евгений | C61: уточнить | D61: Магнитогорск | E61: Самолёт | F61: 12962 | G61: 16375 | H61: 16417 | I61: 20134 | J61: 2400 | K61: 0 | L61: =F61+H61+J61+K61*'Правила и допущения'!$B$3 | M61: =G61+I61+J61+K61*'Правила и допущения'!$B$3 | N61: 16375 | O61: 16966 | P61: 7500 | Q61: 1 | R61: =N61+O61+P61+Q61*'Правила и допущения'!$B$3 | S61: 18 ч 35 мин | T61: 21 ч 00 мин | U61: Обратно удобный: самолёт до Челябинска + автобус (прямые — только 00:40 и 07:40)
A62: 58 | B62: Фирстов Виктор Юрьевич | C62: Златоуст, Челябинск | D62: Челябинск | E62: Самолёт | F62: 6196 | G62: 8991 | H62: 7789 | I62: 10643 | J62: 1800 | K62: 0 | L62: =F62+H62+J62+K62*'Правила и допущения'!$B$3 | M62: =G62+I62+J62+K62*'Правила и допущения'!$B$3 | N62: 12939 | O62: 15466 | P62: 6500 | Q62: 1 | R62: =N62+O62+P62+Q62*'Правила и допущения'!$B$3 | S62: 19 ч 00 мин | T62: 18 ч 15 мин
A63: 59 | B63: Бобошин Сергей Аркадьевич | C63: Курган, Сургут, Тюмень | D63: Тюмень | E63: Самолёт | F63: 5873 | G63: 8712 | H63: 8168 | I63: 11154 | J63: 3000 | K63: 0 | L63: =F63+H63+J63+K63*'Правила и допущения'!$B$3 | M63: =G63+I63+J63+K63*'Правила и допущения'!$B$3 | N63: 10125 | O63: 10818 | P63: 9000 | Q63: 1 | R63: =N63+O63+P63+Q63*'Правила и допущения'!$B$3 | S63: 18 ч 50 мин | T63: 17 ч 10 мин
A64: 60 | B64: Федоров Константин Иванович | C64: уточнить | D64: Нижний Тагил | E64: Самолёт | F64: 7811 | G64: 10789 | H64: 9104 | I64: 12205 | J64: 4400 | K64: 0 | L64: =F64+H64+J64+K64*'Правила и допущения'!$B$3 | M64: =G64+I64+J64+K64*'Правила и допущения'!$B$3 | N64: 11932 | O64: 15996 | P64: 13400 | Q64: 1 | R64: =N64+O64+P64+Q64*'Правила и допущения'!$B$3 | S64: 22 ч 45 мин | T64: 20 ч 50 мин | U64: С группой Екатеринбурга; удобный — ночь в Екатеринбурге накануне (~3 000 ₽)
A65: 61 | B65: Меднов Владимир Александрович | C65: Руководитель ЦР Нижний Новгород | D65: Нижний Новгород | E65: Авто | F65: ='Авто'!J8/2 | G65: ='Авто'!J8/2 | H65: ='Авто'!J8/2 | I65: ='Авто'!J8/2 | J65: 0 | K65: 0 | L65: =F65+H65+J65+K65*'Правила и допущения'!$B$3 | M65: =G65+I65+J65+K65*'Правила и допущения'!$B$3 | N65: ='Авто'!J8/2 | O65: ='Авто'!J8/2 | P65: 0 | Q65: 1 | R65: =N65+O65+P65+Q65*'Правила и допущения'!$B$3 | S65: 12 ч 00 мин | T65: 12 ч 00 мин | U65: Экипаж: Н. Новгород + Владимир (3 чел.). Удобный = обратно 31.10 утром + ночь
A66: 62 | B66: Шабанов Роман Васильевич | C66: уточнить | D66: Владимир | E66: Авто | F66: ='Авто'!J8/2 | G66: ='Авто'!J8/2 | H66: ='Авто'!J8/2 | I66: ='Авто'!J8/2 | J66: 0 | K66: 0 | L66: =F66+H66+J66+K66*'Правила и допущения'!$B$3 | M66: =G66+I66+J66+K66*'Правила и допущения'!$B$3 | N66: ='Авто'!J8/2 | O66: ='Авто'!J8/2 | P66: 0 | Q66: 1 | R66: =N66+O66+P66+Q66*'Правила и допущения'!$B$3 | S66: 7 ч 00 мин | T66: 7 ч 00 мин | U66: Экипаж: Н. Новгород + Владимир (3 чел.). Удобный = обратно 31.10 утром + ночь
A67: 63 | B67: Викторов Максим Сергеевич | C67: уточнить | D67: Ярославль | E67: Поезд | F67: 1106 | G67: 1106 | H67: 3058 | I67: 3058 | J67: 1800 | K67: 0 | L67: =F67+H67+J67+K67*'Правила и допущения'!$B$3 | M67: =G67+I67+J67+K67*'Правила и допущения'!$B$3 | N67: 1106 | O67: 1716 | P67: 1800 | Q67: 1 | R67: =N67+O67+P67+Q67*'Правила и допущения'!$B$3 | S67: 16 ч 00 мин | T67: 14 ч 40 мин | U67: Ярославский вокзал рядом с Казанским; обратно удобный — днём 31.10
A68: 64 | B68: Макеев Сергей Иванович | C68: уточнить | D68: Калуга | E68: Авто | F68: ='Авто'!J9/2 | G68: ='Авто'!J9/2 | H68: ='Авто'!J9/2 | I68: ='Авто'!J9/2 | J68: 0 | K68: 0 | L68: =F68+H68+J68+K68*'Правила и допущения'!$B$3 | M68: =G68+I68+J68+K68*'Правила и допущения'!$B$3 | N68: ='Авто'!J9/2 | O68: ='Авто'!J9/2 | P68: 0 | Q68: 1 | R68: =N68+O68+P68+Q68*'Правила и допущения'!$B$3 | S68: 7 ч 00 мин | T68: 7 ч 00 мин | U68: Экипаж: Калуга. Удобный = обратно 31.10 утром + ночь
B69: ИТОГО по списку | L69: =SUM(L5:L68) | M69: =SUM(M5:M68) | R69: =SUM(R5:R68)
B70: Сотрудников в списке: 64 .

Sheet Маршруты
A1: Город | B1: Чел. | C1: Вариант | D1: Тип | E1: Транспорт | F1: Рейс / поезд | G1: Отправление | H1: Прибытие (время МСК) | I1: Куда прибывает | J1: Цена без багажа / билет, ₽ | K1: Цена с багажом, ₽ | L1: Как добраться до гостиницы | M1: В гостинице (ориентир) | N1: Выход из дома → в гостинице / выезд из гостиницы → дома | O1: Время в пути (дверь–дверь) | P1: Доп. ночь | Q1: Ссылка (Туту.ру) | R1: Примечание | S1: Проверка пробок (Яндекс/2ГИС)
A2: Омск | B2: 1 | C2: Туда | D2: Самый дешёвый | E2: Самолёт, Победа | F2: DP-6522 | G2: 28.10 07:05 (мест.) | H2: 28.10 07:45 | I2: Шереметьево | J2: 7655 | K2: 10548 | L2: Шереметьево: такси ~3 ч или аэроэкспресс → Белорусский + метро → Казанский + электричка | M2: ~11:30 | N2: 28.10 04:05 (мест.) → 28.10 11:30 МСК | O2: 10 ч 25 мин | Q2: https://avia.tutu.ru/f/Omsk/Moskva/?class=Y&travelers=1&route[0]=62-28102026-491 | R2: Ранний подъём (~04:00). Все прямые рейсы 28.10 вылетают до 08:05 | S2: проверить
A3: Омск | B3: 1 | C3: Туда (27.10) | D3: Удобный | E3: Самолёт, Аэрофлот | F3: SU-1689 | G3: 27.10 17:15 (мест.) | H3: 27.10 17:55 | I3: Шереметьево | J3: 10328 | K3: 14270 | L3: Такси ~3 ч (вечер 27.10) | M3: 27.10 ~22:00 | N3: 27.10 14:15 (мест.) → 27.10 22:00 МСК | O3: 10 ч 45 мин | P3: +1 ночь 27→28 | Q3: https://avia.tutu.ru/f/Omsk/Moskva/?class=Y&travelers=1&route[0]=62-27102026-491 | R3: Вылет днём накануне, ночь в гостинице — утром 28.10 отдохнувший
A4: Омск | B4: 1 | C4: Обратно | D4: Самый дешёвый | E4: Самолёт, Победа | F4: DP-6521 | G4: 30.10 23:45 | H4: 31.10 (мест.) | I4: Шереметьево | J4: 9591 | K4: 12638 | L4: Выезд из гостиницы 18:15; в аэропорту за 2 ч до вылета | N4: 30.10 18:15 МСК → 31.10 07:45 (мест.) | O4: 10 ч 30 мин | Q4: https://avia.tutu.ru/f/Moskva/Omsk/?class=Y&travelers=1&route[0]=491-30102026-62 | R4: Ночной рейс сразу после конференции
A5: Омск | B5: 1 | C5: Обратно | D5: Удобный | E5: Самолёт, Победа | F5: DP-6523 | G5: 31.10 22:00 | H5: 01.11 04:20 (мест.) | I5: Шереметьево | J5: 9591 | K5: 12639 | L5: 31.10 днём: электричка + аэроэкспресс или такси ~2 ч 30 мин | N5: 31.10 17:30 МСК → 01.11 06:00 (мест.) | O5: 9 ч 30 мин | P5: +1 ночь 30→31 | Q5: https://avia.tutu.ru/f/Moskva/Omsk/?class=Y&travelers=1&route[0]=491-31102026-62 | R5: Дневных рейсов в Омск нет. День 31.10 на отдых, вечерний вылет | S5: проверить
A6: Уфа | B6: 1 | C6: Туда | D6: Самый дешёвый | E6: Самолёт, Победа | F6: DP-436 | G6: 28.10 07:00 (мест.) | H6: 28.10 07:20 | I6: Внуково | J6: 6638 | K6: 9416 | L6: Внуково: метро → Казанский вокзал + электричка, или такси ~2 ч 45 мин | M6: ~10:45 | N6: 28.10 04:00 (мест.) → 28.10 10:45 МСК | O6: 8 ч 45 мин | Q6: https://avia.tutu.ru/f/Ufa/Moskva/?class=Y&travelers=1&route[0]=93-28102026-491 | R6: Ранний подъём | S6: проверить
A7: Уфа | B7: 1 | C7: Туда | D7: Удобный | E7: Самолёт, S7 | F7: S7-1136 | G7: 28.10 15:55 (мест.) | H7: 28.10 16:15 | I7: Домодедово | J7: 7884 | K7: 11268 | L7: Домодедово: такси 1 ч 45 мин + 40 мин на выход (группа 2–4 чел.) | M7: ~18:40 | N7: 28.10 12:55 (мест.) → 28.10 18:40 МСК | O7: 7 ч 45 мин | Q7: https://avia.tutu.ru/f/Ufa/Moskva/?class=Y&travelers=1&route[0]=93-28102026-491 | R7: Без экскурсии. Для экскурсии: SU-1237 12:45 → SVO 13:05, 8 521 / 11 889 | S7: проверить
A8: Уфа | B8: 1 | C8: Обратно | D8: Самый дешёвый | E8: Самолёт, Победа | F8: DP-435 | G8: 30.10 23:40 | H8: 31.10 (мест.) | I8: Внуково | J8: 8417 | K8: 11288 | L8: Выезд из гостиницы 18:15; в аэропорту за 2 ч до вылета | N8: 30.10 18:15 МСК → 31.10 05:30 (мест.) | O8: 9 ч 15 мин | Q8: https://avia.tutu.ru/f/Moskva/Ufa/?class=Y&travelers=1&route[0]=491-30102026-93 | R8: Ночной рейс
A9: Уфа | B9: 1 | C9: Обратно | D9: Удобный | E9: Самолёт, S7 | F9: S7-1135 | G9: 31.10 11:00 | H9: 31.10 15:10 (мест.) | I9: Домодедово | J9: 8639 | K9: 12118 | L9: 31.10 утро: такси до Домодедово ~1 ч 30 мин | N9: 31.10 07:30 МСК → 31.10 16:50 (мест.) | O9: 7 ч 20 мин | P9: +1 ночь 30→31 | Q9: https://avia.tutu.ru/f/Moskva/Ufa/?class=Y&travelers=1&route[0]=491-31102026-93 | S9: проверить
A10: Ревда (а/п Екатеринбург) | B10: 1 | C10: Туда | D10: Самый дешёвый | E10: Самолёт, Победа | F10: DP-404 | G10: 28.10 06:50 (мест.) | H10: 28.10 07:30 | I10: Внуково | J10: 7113 | K10: 10054 | L10: Внуково: метро → Казанский вокзал + электричка, или такси ~2 ч 45 мин | M10: ~10:55 | N10: 28.10 03:40 (мест.) → 28.10 10:55 МСК | O10: 9 ч 15 мин | Q10: https://avia.tutu.ru/f/Ekaterinburg/Moskva/?class=Y&travelers=1&route[0]=29-28102026-491 | R10: Выезд из Ревды ~03:50 | S10: проверить
A11: Ревда (а/п Екатеринбург) | B11: 1 | C11: Туда | D11: Удобный | E11: Самолёт, Уральские авиалинии | F11: U6-300 | G11: 28.10 12:00 (мест.) | H11: 28.10 12:40 | I11: Домодедово | J11: 10289 | K11: 13395 | L11: Домодедово: такси 1 ч 45 мин + 40 мин на выход (группа 2–4 чел.) | M11: ~15:05 | N11: 28.10 08:50 (мест.) → 28.10 15:05 МСК | O11: 8 ч 15 мин | Q11: https://avia.tutu.ru/f/Ekaterinburg/Moskva/?class=Y&travelers=1&route[0]=29-28102026-491 | R11: Выезд из Ревды ~09:00; к экскурсии успевает | S11: проверить
A12: Ревда (а/п Екатеринбург) | B12: 1 | C12: Обратно | D12: Самый дешёвый | E12: Самолёт, Уральские авиалинии | F12: U6-271 | G12: 30.10 23:45 | H12: 31.10 04:15 (мест.) | I12: Домодедово | J12: 10285 | K12: 13388 | L12: Выезд из гостиницы 18:15; в аэропорту за 2 ч до вылета | N12: 30.10 18:15 МСК → 31.10 06:05 (мест.) | O12: 9 ч 50 мин | Q12: https://avia.tutu.ru/f/Moskva/Ekaterinburg/?class=Y&travelers=1&route[0]=491-30102026-29 | R12: Ночной рейс
A13: Ревда (а/п Екатеринбург) | B13: 1 | C13: Обратно | D13: Удобный | E13: Самолёт, Уральские авиалинии | F13: U6-261 | G13: 31.10 10:00 | H13: 31.10 14:30 (мест.) | I13: Домодедово | J13: 11783 | K13: 15996 | L13: 31.10 утро: такси до Домодедово ~1 ч 30 мин (с группой Екатеринбурга) | N13: 31.10 06:30 МСК → 31.10 16:20 (мест.) | O13: 7 ч 50 мин | P13: +1 ночь 30→31 | Q13: https://avia.tutu.ru/f/Moskva/Ekaterinburg/?class=Y&travelers=1&route[0]=491-31102026-29 | S13: проверить
A14: Новосибирск | B14: 3 | C14: Туда | D14: Самый дешёвый | E14: Самолёт, Победа | F14: DP-6526 | G14: 28.10 07:50 (мест.) | H14: 28.10 08:20 | I14: Шереметьево | J14: 7623 | K14: 10502 | L14: Шереметьево: такси ~3 ч или аэроэкспресс → Белорусский + метро → Казанский + электричка | M14: ~12:00 | N14: 28.10 04:50 (мест.) → 28.10 12:00 МСК | O14: 11 ч 10 мин | Q14: https://avia.tutu.ru/f/Novosibirsk/Moskva/?class=Y&travelers=1&route[0]=58-28102026-491 | R14: Цена за 1 человека | S14: проверить
A15: Новосибирск | B15: 3 | C15: Туда | D15: Удобный | E15: Самолёт, Аэрофлот | F15: SU-1307 | G15: 28.10 10:15 (мест.) | H15: 28.10 10:45 | I15: Шереметьево | J15: 10426 | K15: 14236 | L15: Такси ~3 ч, втроём одна машина | M15: ~14:30 | N15: 28.10 07:15 (мест.) → 28.10 14:30 МСК | O15: 11 ч 15 мин | Q15: https://avia.tutu.ru/f/Novosibirsk/Moskva/?class=Y&travelers=1&route[0]=58-28102026-491 | R15: К экскурсии успевают
A16: Новосибирск | B16: 3 | C16: Обратно | D16: Самый дешёвый | E16: Самолёт, Победа | F16: DP-6525 | G16: 31.10 22:45 | H16: 01.11 (мест.) | I16: Шереметьево | J16: 8607 | K16: 11632 | L16: 31.10 днём: электричка + аэроэкспресс или такси ~2 ч 30 мин | N16: 31.10 18:15 МСК → 01.11 08:45 (мест.) | O16: 10 ч 30 мин | P16: +1 ночь 30→31 | Q16: https://avia.tutu.ru/f/Moskva/Novosibirsk/?class=Y&travelers=1&route[0]=491-31102026-58 | R16: Ночной рейс | S16: проверить
A17: Новосибирск | B17: 3 | C17: Обратно | D17: Удобный | E17: Самолёт, Аэрофлот | F17: SU-1076 | G17: 31.10 12:20 | H17: 31.10 20:25 (мест.) | I17: Шереметьево | J17: 11503 | K17: 15333 | L17: 31.10 утро: такси ~2 ч 30 мин, втроём | N17: 31.10 07:50 МСК → 31.10 22:05 (мест.) | O17: 10 ч 15 мин | P17: +1 ночь 30→31 | Q17: https://avia.tutu.ru/f/Moskva/Novosibirsk/?class=Y&travelers=1&route[0]=491-31102026-58 | R17: Дома вечером 31.10 | S17: проверить
A18: Красноярск | B18: 1 | C18: Туда | D18: Самый дешёвый | E18: Самолёт, Победа | F18: DP-6548 | G18: 28.10 08:10 (мест.) | H18: 28.10 09:25 | I18: Шереметьево | J18: 10652 | K18: 14050 | L18: Шереметьево: такси ~3 ч или аэроэкспресс → Белорусский + метро → Казанский + электричка | M18: ~13:05 | N18: 28.10 05:10 (мест.) → 28.10 13:05 МСК | O18: 11 ч 55 мин | Q18: https://avia.tutu.ru/ | R18: Подъём ~05:00 | S18: проверить
A19: Красноярск | B19: 1 | C19: Туда | D19: Удобный | E19: Самолёт, Аэрофлот | F19: SU-1483 | G19: 28.10 11:05 (мест.) | H19: 28.10 12:20 | I19: Шереметьево | J19: 15358 | K19: 19270 | L19: Шереметьево: такси ~3 ч или аэроэкспресс → Белорусский + метро → Казанский + электричка | M19: ~16:00 | N19: 28.10 08:05 (мест.) → 28.10 16:00 МСК | O19: 11 ч 55 мин | Q19: https://avia.tutu.ru/ | S19: проверить
A20: Красноярск | B20: 1 | C20: Обратно | D20: Самый дешёвый | E20: Самолёт, Победа | F20: DP-6547 | G20: 31.10 22:35 | H20: 01.11 (мест.) | I20: Шереметьево | J20: 9430 | K20: 12647 | L20: 31.10 днём: электричка + аэроэкспресс или такси ~2 ч 30 мин | N20: 31.10 18:05 МСК → 01.11 08:45 (мест.) | O20: 10 ч 40 мин | P20: +1 ночь 30→31 | Q20: https://avia.tutu.ru/ | R20: Ночной рейс | S20: проверить
A21: Красноярск | B21: 1 | C21: Обратно | D21: Удобный | E21: Самолёт, Аэрофлот | F21: SU-1488 | G21: 31.10 13:05 | H21: 31.10 вечер (мест.) | I21: Шереметьево | J21: 20707 | K21: 25343 | L21: 31.10 утро: такси ~2 ч 30 мин | N21: 31.10 08:35 МСК → 31.10 23:15 (мест.) | O21: 10 ч 40 мин | P21: +1 ночь 30→31 | Q21: https://avia.tutu.ru/ | R21: Дома вечером 31.10 | S21: проверить
A22: Абакан | B22: 1 | C22: Туда | D22: Самый дешёвый | E22: Самолёт, S7 | F22: S7-2594 | G22: 28.10 07:15 (мест.) | H22: 28.10 08:25 | I22: Домодедово | J22: 19228 | K22: 25593 | L22: Домодедово: такси 1 ч 45 мин + 40 мин на выход (группа 2–4 чел.) | M22: ~10:50 | N22: 28.10 05:00 (мест.) → 28.10 10:50 МСК | O22: 9 ч 50 мин | Q22: https://avia.tutu.ru/ | R22: Ранний подъём | S22: проверить
A23: Абакан | B23: 1 | C23: Туда | D23: Удобный | E23: Самолёт, Аэрофлот | F23: SU-1479 | G23: 28.10 09:55 (мест.) | H23: 28.10 11:00 | I23: Шереметьево | J23: 21247 | K23: 25201 | L23: Шереметьево: такси ~3 ч или аэроэкспресс → Белорусский + метро → Казанский + электричка | M23: ~14:40 | N23: 28.10 07:40 (мест.) → 28.10 14:40 МСК | O23: 11 ч 00 мин | Q23: https://avia.tutu.ru/ | R23: С багажом дешевле S7 | S23: проверить
A24: Абакан | B24: 1 | C24: Обратно | D24: Самый дешёвый = Удобный | E24: Самолёт, Аэрофлот | F24: SU-1478 | G24: 31.10 23:55 | H24: 01.11 (мест.) | I24: Шереметьево | J24: 21247 | K24: 25201 | L24: 31.10 днём: электричка + аэроэкспресс или такси ~2 ч 30 мин | N24: 31.10 19:25 МСК → 01.11 09:55 (мест.) | O24: 10 ч 30 мин | P24: +1 ночь 30→31 | Q24: https://avia.tutu.ru/ | R24: Дневных рейсов в Абакан нет (есть только вечерние/ночные). День 31.10 на отдых | S24: проверить
A25: Новокузнецк | B25: 1 | C25: Туда | D25: Самый дешёвый = Удобный | E25: Самолёт, S7 | F25: S7-2626 | G25: 28.10 09:00 (мест.) | H25: 28.10 10:00 | I25: Домодедово | J25: 14784 | K25: 20644 | L25: Домодедово: такси 1 ч 45 мин + 40 мин на выход (группа 2–4 чел.) | M25: ~12:25 | N25: 28.10 06:45 (мест.) → 28.10 12:25 МСК | O25: 9 ч 40 мин | Q25: https://avia.tutu.ru/ | S25: проверить
A26: Новокузнецк | B26: 1 | C26: Обратно | D26: Самый дешёвый | E26: Самолёт, S7 | F26: S7-2625 | G26: 30.10 23:35 | H26: 31.10 (мест.) | I26: Домодедово | J26: 14784 | K26: 20644 | L26: Выезд из гостиницы 18:15; в аэропорту за 2 ч до вылета | N26: 30.10 18:15 МСК → 31.10 09:00 (мест.) | O26: 10 ч 45 мин | Q26: https://avia.tutu.ru/ | R26: Ночной рейс сразу после конференции
A27: Новокузнецк | B27: 1 | C27: Обратно | D27: Удобный | E27: Самолёт, Аэрофлот | F27: SU-1458 | G27: 31.10 22:35 | H27: 01.11 (мест.) | I27: Шереметьево | J27: 14806 | K27: 18619 | L27: 31.10 днём: электричка + аэроэкспресс или такси ~2 ч 30 мин | N27: 31.10 18:05 МСК → 01.11 08:00 (мест.) | O27: 9 ч 55 мин | P27: +1 ночь 30→31 | Q27: https://avia.tutu.ru/ | R27: Дневных рейсов нет. День 31.10 на отдых, вечерний вылет | S27: проверить
A28: Иркутск | B28: 5 | C28: Туда | D28: Самый дешёвый | E28: Самолёт, Уральские авиалинии | F28: U6-106 | G28: 28.10 07:35 (мест.) | H28: 28.10 09:10 | I28: Домодедово | J28: 12305 | K28: 15862 | L28: Домодедово: такси 1 ч 45 мин + 40 мин на выход (группа 2–4 чел.) — минивэн на 5 чел. | M28: ~11:35 | N28: 28.10 04:35 (мест.) → 28.10 11:35 МСК | O28: 12 ч 00 мин | Q28: https://avia.tutu.ru/ | R28: Цена за 1 человека | S28: проверить
A29: Иркутск | B29: 5 | C29: Туда | D29: Удобный | E29: Самолёт, Аэрофлот | F29: SU-6732 | G29: 28.10 11:05 (мест.) | H29: 28.10 12:25 | I29: Шереметьево | J29: 13727 | K29: 17607 | L29: Минивэн ~3 ч | M29: ~16:05 | N29: 28.10 08:05 (мест.) → 28.10 16:05 МСК | O29: 13 ч 00 мин | Q29: https://avia.tutu.ru/ | R29: Вылет днём
A30: Иркутск | B30: 5 | C30: Обратно | D30: Самый дешёвый | E30: Самолёт, Уральские авиалинии | F30: U6-105 | G30: 31.10 19:25 | H30: 01.11 (мест.) | I30: Домодедово | J30: 12308 | K30: 15879 | L30: 31.10: минивэн до Домодедово | N30: 31.10 15:55 МСК → 01.11 07:40 (мест.) | O30: 10 ч 45 мин | P30: +1 ночь 30→31 | Q30: https://avia.tutu.ru/ | R30: Ночной перелёт | S30: проверить
A31: Иркутск | B31: 5 | C31: Обратно | D31: Удобный | E31: Самолёт, S7 | F31: S7-3021 | G31: 31.10 12:05 | H31: 31.10 вечер (мест.) | I31: Домодедово | J31: 13005 | K31: 19332 | L31: 31.10 утро: такси до Домодедово ~1 ч 30 мин, минивэн | N31: 31.10 08:35 МСК → 01.11 00:20 (мест.) | O31: 10 ч 45 мин | P31: +1 ночь 30→31 | Q31: https://avia.tutu.ru/ | R31: Дома вечером 31.10 | S31: проверить
A32: Улан-Удэ | B32: 1 | C32: Туда | D32: Самый дешёвый = Удобный | E32: Самолёт, Аэрофлот | F32: SU-1455 | G32: 28.10 10:05 (мест.) | H32: 28.10 11:45 | I32: Шереметьево | J32: 16931 | K32: 21094 | L32: Шереметьево: такси ~3 ч или аэроэкспресс → Белорусский + метро → Казанский + электричка | M32: ~15:25 | N32: 28.10 07:50 (мест.) → 28.10 15:25 МСК | O32: 12 ч 35 мин | Q32: https://avia.tutu.ru/ | S32: проверить
A33: Улан-Удэ | B33: 1 | C33: Обратно | D33: Самый дешёвый | E33: Самолёт, S7 | F33: S7-3033 | G33: 30.10 22:20 | H33: 31.10 (мест.) | I33: Домодедово | J33: 21098 | K33: 28884 | L33: Выезд из гостиницы 18:15; в аэропорту за 2 ч до вылета | N33: 30.10 18:15 МСК → 31.10 10:35 (мест.) | O33: 11 ч 20 мин | Q33: https://avia.tutu.ru/ | R33: Ночной рейс сразу после конференции
A34: Улан-Удэ | B34: 1 | C34: Обратно | D34: Удобный | E34: Самолёт, Аэрофлот | F34: SU-1454 | G34: 31.10 21:55 | H34: 01.11 утро (мест.) | I34: Шереметьево | J34: 16931 | K34: 21094 | L34: 31.10 днём: электричка + аэроэкспресс или такси ~2 ч 30 мин | N34: 31.10 17:25 МСК → 01.11 10:00 (мест.) | O34: 11 ч 35 мин | P34: +1 ночь 30→31 | Q34: https://avia.tutu.ru/ | R34: Дневных рейсов нет. День 31.10 на отдых; прилёт утром | S34: проверить
A35: Чита | B35: 1 | C35: Туда | D35: Самый дешёвый | E35: Самолёт, S7 (пересадка Иркутск) | F35: S7-6426 + S7-3018 | G35: 28.10 03:20 (мест.) | H35: 28.10 10:55 | I35: Домодедово | J35: 17671 | K35: 25050 | L35: Домодедово: такси 1 ч 45 мин + 40 мин на выход (группа 2–4 чел.) | M35: ~13:20 | N35: 28.10 01:05 (мест.) → 28.10 13:20 МСК | O35: 18 ч 15 мин | Q35: https://avia.tutu.ru/f/Chita/Moskva/?class=Y&travelers=1&route[0]=100-28102026-491 | R35: Ночной вылет | S35: проверить
A36: Чита | B36: 1 | C36: Туда | D36: Удобный | E36: Самолёт, Уральские авиалинии, прямой | F36: U6-94 | G36: 28.10 09:20 (мест.) | H36: 28.10 10:20 | I36: Домодедово | J36: 22835 | K36: 28993 | L36: Домодедово: такси 1 ч 45 мин + 40 мин на выход (группа 2–4 чел.) | M36: ~12:45 | N36: 28.10 07:05 (мест.) → 28.10 12:45 МСК | O36: 11 ч 40 мин | Q36: https://avia.tutu.ru/f/Chita/Moskva/?class=Y&travelers=1&route[0]=100-28102026-491 | R36: Прямой рейс днём | S36: проверить
A37: Чита | B37: 1 | C37: Обратно | D37: Самый дешёвый = Удобный | E37: Самолёт, Уральские авиалинии | F37: U6-93 | G37: 31.10 19:40 | H37: 01.11 (мест.) | I37: Домодедово | J37: 22835 | K37: 28993 | L37: 31.10: такси до Домодедово | N37: 31.10 16:10 МСК → 01.11 09:05 (мест.) | O37: 10 ч 55 мин | P37: +1 ночь 30→31 | Q37: https://avia.tutu.ru/f/Moskva/Chita/?class=Y&travelers=1&route[0]=491-31102026-100 | R37: Дневных рейсов нет; вылет вечером после отдыха | S37: проверить
A38: Самара | B38: 1 | C38: Туда (27.10) | D38: Самый дешёвый | E38: Поезд, купе | F38: 015М | G38: 27.10 15:41 | H38: 28.10 05:40 | I38: Москва, Казанский | J38: 3594 | K38: 3594 | L38: Казанский вокзал → электричка до ст. Коломна (490–620 ₽) + такси 10 мин (~300 ₽) (07:22 → 09:15) | M38: ~09:30 | N38: 27.10 14:55 (мест.) → 28.10 09:30 МСК | O38: 19 ч 35 мин | P38: ранний заезд | Q38: https://www.tutu.ru/poezda/ | R38: Ночь в поезде | S38: проверить
A39: Самара | B39: 1 | C39: Туда | D39: Удобный | E39: Самолёт, Победа | F39: DP-422 | G39: 28.10 14:45 (мест.) | H39: 28.10 15:45 | I39: Внуково | J39: 4644 | K39: 7347 | L39: Внуково: метро → Казанский вокзал + электричка, или такси ~2 ч 45 мин | M39: ~19:10 | N39: 28.10 11:45 (мест.) → 28.10 19:10 МСК | O39: 8 ч 25 мин | Q39: https://avia.tutu.ru/f/Samara/Moskva/?class=Y&travelers=1&route[0]=74-28102026-491 | R39: Для экскурсии: SU-1603 10:25 → SVO 11:15, 6 454 / 9 763 | S39: проверить
A40: Самара | B40: 1 | C40: Обратно | D40: Самый дешёвый | E40: Поезд, купе | F40: 014Е | G40: 30.10 21:40 | H40: 31.10 12:18 | I40: Москва, Казанский | J40: 6905 | K40: 6905 | L40: Электричка 18:43 → Казанский 20:47 | N40: 30.10 18:15 МСК → 31.10 13:05 (мест.) | O40: 17 ч 50 мин | Q40: https://www.tutu.ru/poezda/ | R40: Ночь в поезде
A41: Самара | B41: 1 | C41: Обратно | D41: Удобный | E41: Самолёт, Победа | F41: DP-6581 | G41: 31.10 14:15 | H41: 31.10 17:00 (мест.) | I41: Шереметьево | J41: 5550 | K41: 8293 | L41: 31.10 днём: электричка + аэроэкспресс или такси ~2 ч 30 мин | N41: 31.10 09:45 МСК → 31.10 18:40 (мест.) | O41: 7 ч 55 мин | P41: +1 ночь 30→31 | Q41: https://avia.tutu.ru/f/Moskva/Samara/?class=Y&travelers=1&route[0]=491-31102026-74 | R41: Также SU-1604 10:10, 6 410 / 9 760 | S41: проверить
A42: Саратов | B42: 2 | C42: Туда (27.10) | D42: Самый дешёвый | E42: Поезд, купе (сидячий 2 717) | F42: 135Ж | G42: 27.10 15:20 | H42: 28.10 07:22 | I42: Москва, Павелецкий | J42: 4013 | K42: 4013 | L42: Павелецкий → метро до Комсомольской (~20 мин) → электричка от Казанского + такси (08:47 РЭКС → 10:28) | M42: ~10:45 | N42: 27.10 14:35 (мест.) → 28.10 10:45 МСК | O42: 21 ч 10 мин | Q42: https://www.tutu.ru/poezda/ | R42: Ночь в поезде | S42: проверить
A43: Саратов | B43: 2 | C43: Туда | D43: Удобный | E43: Самолёт, Победа | F43: DP-6864 | G43: 28.10 17:30 (мест.) | H43: 28.10 18:20 | I43: Шереметьево | J43: 5658 | K43: 8442 | L43: Такси ~3 ч, вдвоём | M43: ~22:00 | N43: 28.10 15:15 (мест.) → 28.10 22:00 МСК | O43: 7 ч 45 мин | Q43: https://avia.tutu.ru/f/Saratov/Moskva/?class=Y&travelers=1&route[0]=77-28102026-491 | R43: Для экскурсии: SU-1357 11:05 → SVO 11:50, 8 078 / 11 390
A44: Саратов | B44: 2 | C44: Обратно | D44: Самый дешёвый = Удобный | E44: Самолёт, Победа | F44: DP-475 | G44: 31.10 17:55 | H44: 31.10 20:35 (мест.) | I44: Внуково | J44: 5012 | K44: 7630 | L44: 31.10 днём: такси до Внуково ~2 ч 15 мин или электричка + метро | N44: 31.10 13:40 МСК → 31.10 22:00 (мест.) | O44: 7 ч 20 мин | P44: +1 ночь 30→31 | Q44: https://avia.tutu.ru/f/Moskva/Saratov/?class=Y&travelers=1&route[0]=491-31102026-77 | R44: 30.10 уехать нельзя: последний поезд 19:27, рейсы до 18:00 | S44: проверить
A45: Казань | B45: 1 | C45: Туда | D45: Самый дешёвый | E45: Самолёт, Nordwind | F45: N4-64 | G45: 28.10 08:05 | H45: 28.10 09:45 | I45: Шереметьево | J45: 3265 | K45: 5995 | L45: Шереметьево: такси ~3 ч или аэроэкспресс → Белорусский + метро → Казанский + электричка | M45: ~13:30 | N45: 28.10 05:05 МСК → 28.10 13:30 МСК | O45: 8 ч 25 мин | Q45: https://avia.tutu.ru/f/Kazan/Moskva/?class=Y&travelers=1&route[0]=33-28102026-491 | R45: Дешевле поезда; подъём ~05:30 | S45: проверить
A46: Казань | B46: 1 | C46: Туда | D46: Удобный | E46: Самолёт, Nordwind | F46: N4-60 | G46: 28.10 10:10 | H46: 28.10 11:55 | I46: Шереметьево | J46: 4078 | K46: 7021 | L46: Шереметьево: такси ~3 ч или аэроэкспресс → Белорусский + метро → Казанский + электричка | M46: ~15:35 | N46: 28.10 07:10 МСК → 28.10 15:35 МСК | O46: 8 ч 25 мин | Q46: https://avia.tutu.ru/f/Kazan/Moskva/?class=Y&travelers=1&route[0]=33-28102026-491 | R46: К экскурсии успевает | S46: проверить
A47: Казань | B47: 1 | C47: Обратно | D47: Самый дешёвый | E47: Поезд, купе | F47: 130Х | G47: 31.10 00:20 | H47: 31.10 утро | I47: Москва, Казанский | J47: 4270 | K47: 4270 | L47: РЭКС 21:01 → Казанский 22:38 | N47: 30.10 20:30 МСК → 31.10 13:15 МСК | O47: 16 ч 45 мин | Q47: https://www.tutu.ru/poezda/ | R47: Ночь в поезде
A48: Казань | B48: 1 | C48: Обратно | D48: Удобный | E48: Самолёт, Победа | F48: DP-6843 | G48: 31.10 17:30 | H48: 31.10 19:10 | I48: Шереметьево | J48: 5056 | K48: 7722 | L48: 31.10 днём: электричка + аэроэкспресс или такси ~2 ч 30 мин | N48: 31.10 13:00 МСК → 31.10 20:50 МСК | O48: 7 ч 50 мин | P48: +1 ночь 30→31 | Q48: https://avia.tutu.ru/f/Moskva/Kazan/?class=Y&travelers=1&route[0]=491-31102026-33 | R48: Также N4-63 16:10, 7 323 / 10 492 | S48: проверить
A49: Ижевск | B49: 1 | C49: Туда | D49: Самый дешёвый = Удобный | E49: Самолёт, S7 | F49: S7-1166 | G49: 28.10 18:55 (мест.) | H49: 28.10 20:05 | I49: Домодедово | J49: 8158 | K49: 11683 | L49: Домодедово: такси 1 ч 45 мин + 40 мин на выход (группа 2–4 чел.) | M49: ~22:30 | N49: 28.10 16:40 (мест.) → 28.10 22:30 МСК | O49: 6 ч 50 мин | Q49: https://avia.tutu.ru/f/Izhevsk/Moskva/?class=Y&travelers=1&route[0]=30-28102026-491 | R49: Без экскурсии. Для экскурсии: SU-1295 10:40 → SVO 11:35, 9 802 / 13 186 | S49: проверить
A50: Ижевск | B50: 1 | C50: Обратно | D50: Самый дешёвый = Удобный | E50: Самолёт, S7 | F50: S7-1165 | G50: 31.10 15:10 | H50: 31.10 18:10 (мест.) | I50: Домодедово | J50: 8158 | K50: 11683 | L50: 31.10: такси до Домодедово | N50: 31.10 11:40 МСК → 31.10 19:35 (мест.) | O50: 6 ч 55 мин | P50: +1 ночь 30→31 | Q50: https://avia.tutu.ru/f/Moskva/Izhevsk/?class=Y&travelers=1&route[0]=491-31102026-30 | R50: Вечером 30.10 рейсов нет | S50: проверить
A51: Набережные Челны (а/п Бегишево) | B51: 1 | C51: Туда | D51: Самый дешёвый = Удобный | E51: Самолёт, Победа | F51: DP-6846 | G51: 28.10 16:30 | H51: 28.10 18:30 | I51: Шереметьево | J51: 4517 | K51: 7237 | L51: Шереметьево: такси ~3 ч или аэроэкспресс → Белорусский + метро → Казанский + электричка | M51: ~22:10 | N51: 28.10 14:15 МСК → 28.10 22:10 МСК | O51: 7 ч 55 мин | Q51: https://avia.tutu.ru/f/Nizhnekamsk/Moskva/?class=Y&travelers=1&route[0]=537-28102026-491 | R51: Без экскурсии. Для экскурсии: SU-6248 09:55, 8 847 / 12 189 | S51: проверить
A52: Набережные Челны (а/п Бегишево) | B52: 1 | C52: Обратно | D52: Самый дешёвый = Удобный | E52: Самолёт, Победа | F52: DP-6845 | G52: 31.10 14:10 | H52: 31.10 16:00 | I52: Шереметьево | J52: 5056 | K52: 7775 | L52: 31.10 днём: электричка + аэроэкспресс или такси ~2 ч 30 мин | N52: 31.10 09:40 МСК → 31.10 17:25 МСК | O52: 7 ч 45 мин | P52: +1 ночь 30→31 | Q52: https://avia.tutu.ru/f/Moskva/Nizhnekamsk/?class=Y&travelers=1&route[0]=491-31102026-537 | R52: Вечером 30.10 рейсов нет | S52: проверить
A53: Оренбург | B53: 1 | C53: Туда | D53: Самый дешёвый = Удобный | E53: Самолёт, Nordwind | F53: N4-78 | G53: 28.10 18:35 (мест.) | H53: 28.10 18:55 | I53: Шереметьево | J53: 7050 | K53: 9636 | L53: Шереметьево: такси ~3 ч или аэроэкспресс → Белорусский + метро → Казанский + электричка | M53: ~22:35 | N53: 28.10 16:20 (мест.) → 28.10 22:35 МСК | O53: 8 ч 15 мин | Q53: https://avia.tutu.ru/ | R53: Без экскурсии. Для экскурсии: SU-1247 12:20, 11 352 / 14 698 | S53: проверить
A54: Оренбург | B54: 1 | C54: Обратно | D54: Самый дешёвый | E54: Самолёт, Северный ветер | F54: 5N-231 | G54: 31.10 02:40 | H54: 31.10 утро | I54: Шереметьево | J54: 8429 | L54: 30.10 вечер: электричка + аэроэкспресс | N54: 30.10 19:00 МСК → 31.10 08:10 (мест.) | O54: 11 ч 10 мин | Q54: https://avia.tutu.ru/ | R54: Ночной рейс, гостиница не нужна. Проверить наличие
A55: Оренбург | B55: 1 | C55: Обратно | D55: Удобный | E55: Самолёт, Аэрофлот | F55: SU-1248 | G55: 31.10 15:30 | H55: 31.10 19:45 (мест.) | I55: Шереметьево | J55: 12697 | K55: 15985 | L55: 31.10 днём: электричка + аэроэкспресс или такси ~2 ч 30 мин | N55: 31.10 11:00 МСК → 31.10 21:10 (мест.) | O55: 8 ч 10 мин | P55: +1 ночь 30→31 | Q55: https://avia.tutu.ru/ | S55: проверить
A56: Ульяновск | B56: 2 | C56: Туда | D56: Самый дешёвый = Удобный | E56: Самолёт, Победа | F56: DP-466 | G56: 28.10 11:10 (мест.) | H56: 28.10 11:50 | I56: Внуково | J56: 4938 | K56: 7618 | L56: Внуково: метро → Казанский вокзал + электричка, или такси ~2 ч 45 мин (вдвоём — такси) | M56: ~15:15 | N56: 28.10 08:55 (мест.) → 28.10 15:15 МСК | O56: 7 ч 20 мин | Q56: https://avia.tutu.ru/f/Ulyanovsk/Moskva/?class=Y&travelers=1&route[0]=88-28102026-491 | R56: К экскурсии успевают | S56: проверить
A57: Ульяновск | B57: 2 | C57: Обратно | D57: Самый дешёвый = Удобный | E57: Самолёт, Победа | F57: DP-485 | G57: 31.10 19:35 | H57: 31.10 22:15 (мест.) | I57: Внуково | J57: 5628 | K57: 8367 | L57: 31.10 днём: такси до Внуково ~2 ч 15 мин или электричка + метро | N57: 31.10 15:20 МСК → 31.10 23:40 (мест.) | O57: 7 ч 20 мин | P57: +1 ночь 30→31 | Q57: https://avia.tutu.ru/f/Moskva/Ulyanovsk/?class=Y&travelers=1&route[0]=491-31102026-88 | R57: 30.10 уехать нельзя | S57: проверить
A58: Чебоксары | B58: 1 | C58: Туда | D58: Самый дешёвый = Удобный | E58: Самолёт, Победа | F58: DP-6808 | G58: 28.10 10:10 | H58: 28.10 11:45 | I58: Шереметьево | J58: 4214 | K58: 6754 | L58: Шереметьево: такси ~3 ч или аэроэкспресс → Белорусский + метро → Казанский + электричка | M58: ~15:30 | N58: 28.10 07:55 МСК → 28.10 15:30 МСК | O58: 7 ч 35 мин | Q58: https://avia.tutu.ru/f/Cheboksary/Moskva/?class=Y&travelers=1&route[0]=97-28102026-491 | R58: Дешевле поезда, к экскурсии успевает | S58: проверить
A59: Чебоксары | B59: 1 | C59: Обратно | D59: Самый дешёвый | E59: Поезд, купе | F59: 072Г | G59: 31.10 00:10 | H59: 31.10 днём | I59: Москва, Казанский | J59: 3884 | K59: 3884 | L59: Электричка 20:10 → 22:30 или РЭКС 21:01 → 22:38 | N59: 30.10 19:40 МСК → 31.10 12:45 МСК | O59: 17 ч 05 мин | Q59: https://www.tutu.ru/poezda/ | R59: Ночь в поезде
A60: Чебоксары | B60: 1 | C60: Обратно | D60: Удобный | E60: Самолёт, Победа | F60: DP-6815 | G60: 31.10 19:30 | H60: 31.10 20:55 | I60: Шереметьево | J60: 4214 | K60: 6754 | L60: 31.10 днём: электричка + аэроэкспресс или такси ~2 ч 30 мин | N60: 31.10 15:00 МСК → 31.10 22:20 МСК | O60: 7 ч 20 мин | P60: +1 ночь 30→31 | Q60: https://avia.tutu.ru/f/Moskva/Cheboksary/?class=Y&travelers=1&route[0]=491-31102026-97 | R60: Также SU-1586 16:25, 6 582 / 9 919 | S60: проверить
A61: Астрахань | B61: 1 | C61: Туда | D61: Самый дешёвый = Удобный | E61: Самолёт, Победа | F61: DP-6962 | G61: 28.10 12:00 (мест.) | H61: 28.10 13:45 | I61: Шереметьево | J61: 7124 | K61: 9710 | L61: Шереметьево: такси ~3 ч или аэроэкспресс → Белорусский + метро → Казанский + электричка | M61: ~17:25 | N61: 28.10 09:45 (мест.) → 28.10 17:25 МСК | O61: 8 ч 40 мин | Q61: https://avia.tutu.ru/f/Astrakhan/Moskva/?class=Y&travelers=1&route[0]=12-28102026-491 | S61: проверить
A62: Астрахань | B62: 1 | C62: Обратно | D62: Самый дешёвый = Удобный | E62: Самолёт, Победа | F62: DP-6963 | G62: 31.10 13:50 | H62: 31.10 17:30 (мест.) | I62: Шереметьево | J62: 7124 | K62: 9710 | L62: 31.10 днём: электричка + аэроэкспресс или такси ~2 ч 30 мин | N62: 31.10 09:20 МСК → 31.10 18:55 (мест.) | O62: 8 ч 35 мин | P62: +1 ночь 30→31 | Q62: https://avia.tutu.ru/f/Moskva/Astrakhan/?class=Y&travelers=1&route[0]=491-31102026-12 | R62: Вечером 30.10 подходящих рейсов нет | S62: проверить
A63: Волгоград | B63: 1 | C63: Туда | D63: Самый дешёвый = Удобный | E63: Самолёт, Победа | F63: DP-6966 | G63: 28.10 10:10 | H63: 28.10 12:10 | I63: Шереметьево | J63: 6406 | K63: 9061 | L63: Шереметьево: такси ~3 ч или аэроэкспресс → Белорусский + метро → Казанский + электричка | M63: ~15:50 | N63: 28.10 07:10 МСК → 28.10 15:50 МСК | O63: 8 ч 40 мин | Q63: https://avia.tutu.ru/f/Volgograd/Moskva/?class=Y&travelers=1&route[0]=23-28102026-491 | R63: Дешевле ночного поезда (6 615) | S63: проверить
A64: Волгоград | B64: 1 | C64: Обратно | D64: Самый дешёвый = Удобный | E64: Самолёт, Победа | F64: DP-6969 | G64: 31.10 18:35 | H64: 31.10 20:35 | I64: Шереметьево | J64: 7155 | K64: 9893 | L64: 31.10 днём: электричка + аэроэкспресс или такси ~2 ч 30 мин | N64: 31.10 14:05 МСК → 31.10 22:15 МСК | O64: 8 ч 10 мин | P64: +1 ночь 30→31 | Q64: https://avia.tutu.ru/f/Moskva/Volgograd/?class=Y&travelers=1&route[0]=491-31102026-23 | R64: 30.10 уехать нельзя. Также S7-2143 DME 11:05, 9 889 / 13 255 | S64: проверить
A65: Белгород | B65: 1 | C65: Туда | D65: Самый дешёвый = Удобный | E65: Ласточка, сидячий | F65: 746В | G65: 28.10 07:32 | H65: 28.10 14:37 | I65: Москва, Курский | J65: 2739 | K65: 2739 | L65: Курский → Казанский ~30 мин → электричка + такси | M65: ~17:40 | N65: 28.10 06:45 МСК → 28.10 17:40 МСК | O65: 10 ч 55 мин | Q65: https://www.tutu.ru/poezda/rasp_d.php?date=28.10.2026&nnst1=2014370&nnst2=2000000 | R65: ~650 км — больше лимита для машины | S65: проверить
A66: Белгород | B66: 1 | C66: Обратно | D66: Самый дешёвый | E66: Поезд, купе | F66: 057Щ | G66: 30.10 22:40 | H66: 31.10 14:30 | I66: Белгород | J66: 3947 | K66: 3947 | L66: Электричка 18:43 → 20:47, метро до Павелецкого | N66: 30.10 18:15 МСК → 31.10 15:15 МСК | O66: 21 ч 00 мин | Q66: https://www.tutu.ru/poezda/rasp_d.php?date=30.10.2026&nnst1=2000000&nnst2=2014370 | R66: Ночь в поезде
A67: Белгород | B67: 1 | C67: Обратно | D67: Удобный | E67: Ласточка, сидячий | F67: 741А | G67: 31.10 11:46 | H67: 31.10 19:06 | I67: Белгород | J67: 2674 | K67: 2674 | L67: 31.10 утро: электричка до Москвы + метро до Курского | N67: 31.10 08:45 МСК → 31.10 19:50 МСК | O67: 11 ч 05 мин | P67: +1 ночь 30→31 | Q67: https://www.tutu.ru/poezda/rasp_d.php?date=31.10.2026&nnst1=2000000&nnst2=2014370 | R67: Днём, без ночи в дороге
A68: Донецк (ДНР) | B68: 1 | C68: Туда (27.10) | D68: Самый дешёвый | E68: Автобус (сидячее место) | F68: рейс ~09:15–12:00 | G68: 27.10 ~09:15–12:00 | H68: 28.10 06:00–07:00 | I68: Москва, АС «Новоясеневская» | J68: 3500 | K68: 3500 | L68: Метро до Комсомольской → электричка 08:47 РЭКС / 09:48 → такси | M68: ~11:00–12:00 | N68: 27.10 08:30 МСК → 28.10 11:30 МСК | O68: 27 ч 00 мин | Q68: https://vekspress-bus.ru/marshrutyi/doneczk-moskva.html | R68: ~20 ч в автобусе, ночь сидя. Многие рейсы через день — уточнить | S68: проверить
A69: Донецк (ДНР) | B69: 1 | C69: Туда (27.10) | D69: Удобный | E69: Автобус/такси до Ростова + поезд «Ингушетия», купе | F69: 145С | G69: 27.10 ~06:00 из Донецка; поезд 10:30 | H69: 28.10 07:24 | I69: Москва, Казанский | J69: 6793 | K69: 6793 | L69: Казанский вокзал → электричка до ст. Коломна (490–620 ₽) + такси 10 мин (~300 ₽) (08:47 РЭКС → 10:28) | M69: ~10:45 | N69: 27.10 05:30 МСК → 28.10 10:45 МСК | O69: 29 ч 15 мин | Q69: https://www.tutu.ru/poezda/rasp_d.php?date=27.10.2026&nnst1=2064000&nnst2=2000000 | R69: Ночь в купе — дневного варианта из Донецка нет. Донецк → Ростов ~4 ч (~1 500 ₽) | S69: проверить
A70: Донецк (ДНР) | B70: 1 | C70: Обратно | D70: Самый дешёвый | E70: Автобус (сидячее место) | F70: рейс ~11:00–13:00 | G70: 31.10 днём | H70: 01.11 утро | I70: АС «Новоясеневская» → Донецк | J70: 4000 | K70: 4000 | L70: 31.10: электричка до Казанского + метро | N70: 31.10 08:30 МСК → 01.11 09:00 МСК | O70: 24 ч 30 мин | P70: +1 ночь 30→31 | Q70: https://vekspress-bus.ru/marshrutyi/doneczk-moskva.html | R70: Ночь сидя в автобусе
A71: Донецк (ДНР) | B71: 1 | C71: Обратно | D71: Удобный | E71: Поезд «Ингушетия», купе + автобус до Донецка | F71: 146Э | G71: 30.10 23:23 | H71: 31.10 19:35 (Ростов) | I71: Ростов-Главный | J71: 7132 | K71: 7132 | L71: Электричка 18:43 → Казанский 20:47 | N71: 30.10 18:15 МСК → 01.11 00:00 МСК | O71: 29 ч 45 мин | Q71: https://www.tutu.ru/poezda/rasp_d.php?date=30.10.2026&nnst1=2000000&nnst2=2064000 | R71: Ночь в купе; дома ~00:00. Также 092М «Таврия» 23:30, 9 721 ₽
A72: Екатеринбург (группа) | B72: 10 | C72: Туда | D72: Самый дешёвый | E72: Самолёт, Уральские авиалинии | F72: U6-264 | G72: 28.10 06:50 (мест.) | H72: 28.10 07:25 | I72: Домодедово | J72: 7811 | K72: 10789 | L72: Домодедово: такси 1 ч 45 мин + 40 мин на выход (группа 2–4 чел.) — 2 минивэна | M72: ~09:50 | N72: 28.10 03:50 (мест.) → 28.10 09:50 МСК | O72: 8 ч 00 мин | Q72: https://avia.tutu.ru/f/Ekaterinburg/Moskva/?class=Y&travelers=1&route[0]=29-28102026-491 | R72: Подъём ~03:30. Цена одного билета; 10 билетов на один рейс — покупать заранее, пока есть места по этой цене | S72: проверить
A73: Екатеринбург (группа) | B73: 10 | C73: Туда | D73: Удобный | E73: Самолёт, Уральские авиалинии | F73: U6-272 | G73: 28.10 09:30 (мест.) | H73: 28.10 10:10 | I73: Домодедово | J73: 8875 | K73: 11932 | L73: Домодедово: такси 1 ч 45 мин + 40 мин на выход (группа 2–4 чел.) — 2 минивэна | M73: ~12:40 | N73: 28.10 06:30 (мест.) → 28.10 12:40 МСК | O73: 8 ч 10 мин | Q73: https://avia.tutu.ru/f/Ekaterinburg/Moskva/?class=Y&travelers=1&route[0]=29-28102026-491 | R73: Подъём ~06:00; к экскурсии успевают. Также U6-300 12:00, 10 289 / 13 395 | S73: проверить
A74: Екатеринбург (группа) | B74: 10 | C74: Обратно | D74: Самый дешёвый | E74: Самолёт, Победа | F74: DP-403 | G74: 30.10 23:50 | H74: 31.10 04:20 (мест.) | I74: Внуково | J74: 9104 | K74: 12205 | L74: Выезд из гостиницы 18:15; в аэропорту за 2 ч до вылета — минивэн до Внуково | N74: 30.10 18:15 МСК → 31.10 06:00 (мест.) | O74: 9 ч 45 мин | Q74: https://avia.tutu.ru/f/Moskva/Ekaterinburg/?class=Y&travelers=1&route[0]=491-30102026-29 | R74: Ночной рейс | S74: проверить
A75: Екатеринбург (группа) | B75: 10 | C75: Обратно | D75: Удобный | E75: Самолёт, Уральские авиалинии | F75: U6-261 | G75: 31.10 10:00 | H75: 31.10 14:30 (мест.) | I75: Домодедово | J75: 11783 | K75: 15996 | L75: 31.10 утро: такси до Домодедово ~1 ч 30 мин, минивэн | N75: 31.10 06:30 МСК → 31.10 16:10 (мест.) | O75: 7 ч 40 мин | P75: +1 ночь 30→31 | Q75: https://avia.tutu.ru/f/Moskva/Ekaterinburg/?class=Y&travelers=1&route[0]=491-31102026-29 | R75: Цена одного билета. Также U6-273 08:25 | S75: проверить
A76: Нижний Тагил | B76: 1 | C76: Подвоз к группе | D76: — | E76: Электричка/такси до Кольцово | G76: 27.10 вечер (удобный) или 28.10 ~03:00 (эконом) | H76: до вылета | I76: Екатеринбург, Кольцово | J76: 1200 | K76: 4000 | L76: ~150 км: электричка + автобус (~1 200 ₽) или такси (~4 000 ₽) | R76: Для удобного варианта — приехать в Екатеринбург накануне | S76: проверить
A77: Магнитогорск | B77: 1 | C77: Туда | D77: Самый дешёвый = Удобный | E77: Самолёт, Азимут | F77: A4-7062 | G77: 28.10 12:20 (мест.) | H77: 28.10 13:00 | I77: Внуково | J77: 12962 | K77: 16375 | L77: Внуково: метро → Казанский вокзал + электричка, или такси ~2 ч 45 мин | M77: ~16:25 | N77: 28.10 10:05 (мест.) → 28.10 16:25 МСК | O77: 8 ч 20 мин | Q77: https://avia.tutu.ru/f/Magnitogorsk/Moskva/?class=Y&travelers=1&route[0]=45-28102026-491 | R77: Выезд из дома ~10:00. Другие рейсы неудобны (06:15) | S77: проверить
A78: Магнитогорск | B78: 1 | C78: Обратно | D78: Самый дешёвый | E78: Самолёт, Аэрофлот | F78: SU-1428 | G78: 31.10 00:40 | H78: 31.10 05:05 (мест.) | I78: Шереметьево | J78: 16417 | K78: 20134 | L78: Выезд из гостиницы 18:15; в аэропорту за 2 ч до вылета | N78: 30.10 18:15 МСК → 31.10 06:30 (мест.) | O78: 10 ч 15 мин | Q78: https://avia.tutu.ru/f/Moskva/Magnitogorsk/?class=Y&travelers=1&route[0]=491-31102026-45 | R78: Ночной рейс сразу после конференции
A79: Магнитогорск | B79: 1 | C79: Обратно | D79: Удобный | E79: Самолёт до Челябинска + автобус | F79: SU-1420 | G79: 31.10 10:50 | H79: 31.10 15:25 Челябинск (мест.), дома ~21:00 | I79: Шереметьево | J79: 13288 | K79: 16966 | L79: 31.10 днём: электричка + аэроэкспресс или такси ~2 ч 30 мин | N79: 31.10 06:20 МСК → 31.10 21:00 (мест.) | O79: 12 ч 40 мин | P79: +1 ночь 30→31 | Q79: https://avia.tutu.ru/f/Moskva/Chelyabinsk/?class=Y&travelers=1&route[0]=491-31102026-98 | R79: Прямые рейсы в Магнитогорск — только 00:40 и 07:40. Челябинск → Магнитогорск автобус ~4,5 ч, ~1 500 ₽ (включено) | S79: проверить
A80: Челябинск | B80: 1 | C80: Туда | D80: Самый дешёвый | E80: Самолёт, Победа | F80: DP-414 | G80: 28.10 06:30 (мест.) | H80: 28.10 07:15 | I80: Внуково | J80: 6196 | K80: 8991 | L80: Внуково: метро → Казанский вокзал + электричка, или такси ~2 ч 45 мин | M80: ~10:40 | N80: 28.10 03:30 (мест.) → 28.10 10:40 МСК | O80: 9 ч 10 мин | Q80: https://avia.tutu.ru/f/Chelyabinsk/Moskva/?class=Y&travelers=1&route[0]=98-28102026-491 | R80: Ранний подъём | S80: проверить
A81: Челябинск | B81: 1 | C81: Туда | D81: Удобный | E81: Самолёт, Аэрофлот | F81: SU-1421 | G81: 28.10 16:20 (мест.) | H81: 28.10 17:10 | I81: Шереметьево | J81: 9292 | K81: 12939 | L81: Шереметьево: такси ~3 ч или аэроэкспресс → Белорусский + метро → Казанский + электричка | M81: ~20:50 | N81: 28.10 13:20 (мест.) → 28.10 20:50 МСК | O81: 9 ч 30 мин | Q81: https://avia.tutu.ru/f/Chelyabinsk/Moskva/?class=Y&travelers=1&route[0]=98-28102026-491 | R81: Без экскурсии. Для экскурсии: SU-1535 12:30, 10 408 / 14 081 | S81: проверить
A82: Челябинск | B82: 1 | C82: Обратно | D82: Самый дешёвый | E82: Самолёт, Победа | F82: DP-413 | G82: 30.10 23:45 | H82: 31.10 04:25 (мест.) | I82: Внуково | J82: 7789 | K82: 10643 | L82: Выезд из гостиницы 18:15; в аэропорту за 2 ч до вылета | N82: 30.10 18:15 МСК → 31.10 06:05 (мест.) | O82: 9 ч 50 мин | Q82: https://avia.tutu.ru/f/Moskva/Chelyabinsk/?class=Y&travelers=1&route[0]=491-30102026-98 | R82: Ночной рейс
A83: Челябинск | B83: 1 | C83: Обратно | D83: Удобный | E83: Самолёт, Аэрофлот | F83: SU-1420 | G83: 31.10 10:50 | H83: 31.10 15:25 (мест.) | I83: Шереметьево | J83: 11788 | K83: 15466 | L83: 31.10 днём: электричка + аэроэкспресс или такси ~2 ч 30 мин | N83: 31.10 06:20 МСК → 31.10 17:05 (мест.) | O83: 8 ч 45 мин | P83: +1 ночь 30→31 | Q83: https://avia.tutu.ru/f/Moskva/Chelyabinsk/?class=Y&travelers=1&route[0]=491-31102026-98 | S83: проверить
A84: Тюмень | B84: 1 | C84: Туда | D84: Самый дешёвый | E84: Самолёт, Победа | F84: DP-6562 | G84: 28.10 06:25 (мест.) | H84: 28.10 07:30 | I84: Шереметьево | J84: 5873 | K84: 8712 | L84: Шереметьево: такси ~3 ч или аэроэкспресс → Белорусский + метро → Казанский + электричка | M84: ~11:10 | N84: 28.10 04:10 (мест.) → 28.10 11:10 МСК | O84: 9 ч 00 мин | Q84: https://avia.tutu.ru/f/Tyumen/Moskva/?class=Y&travelers=1&route[0]=86-28102026-491 | R84: Ранний подъём | S84: проверить
A85: Тюмень | B85: 1 | C85: Туда | D85: Удобный | E85: Самолёт, ЮТэйр | F85: UT-464 | G85: 28.10 18:00 (мест.) | H85: 28.10 18:55 | I85: Внуково | J85: 7065 | K85: 10125 | L85: Такси ~2 ч 45 мин | M85: ~22:30 | N85: 28.10 15:45 (мест.) → 28.10 22:30 МСК | O85: 8 ч 45 мин | Q85: https://avia.tutu.ru/f/Tyumen/Moskva/?class=Y&travelers=1&route[0]=86-28102026-491 | R85: Без экскурсии. Для экскурсии: SU-1505 13:25, 9 980 / 13 589
A86: Тюмень | B86: 1 | C86: Обратно | D86: Самый дешёвый | E86: Самолёт, Победа | F86: DP-6561 | G86: 30.10 23:50 | H86: 31.10 04:40 (мест.) | I86: Шереметьево | J86: 8168 | K86: 11154 | L86: Выезд из гостиницы 18:15; в аэропорту за 2 ч до вылета | N86: 30.10 18:15 МСК → 31.10 06:05 (мест.) | O86: 9 ч 50 мин | Q86: https://avia.tutu.ru/f/Moskva/Tyumen/?class=Y&travelers=1&route[0]=491-30102026-86 | R86: Ночной рейс, впритык по правилу 2 ч
A87: Тюмень | B87: 1 | C87: Обратно | D87: Удобный | E87: Самолёт, ЮТэйр | F87: UT-463 | G87: 31.10 10:00 | H87: 31.10 14:45 (мест.) | I87: Внуково | J87: 7208 | K87: 10818 | L87: 31.10 днём: такси до Внуково ~2 ч 15 мин или электричка + метро | N87: 31.10 05:45 МСК → 31.10 16:10 (мест.) | O87: 8 ч 25 мин | P87: +1 ночь 30→31 | Q87: https://avia.tutu.ru/f/Moskva/Tyumen/?class=Y&travelers=1&route[0]=491-31102026-86 | S87: проверить
A88: Санкт-Петербург | B88: 1 | C88: Туда | D88: Самый дешёвый | E88: Ласточка, сидячий | F88: 723Р | G88: 28.10 05:35 | H88: 28.10 11:13 | I88: Москва, Ленинградский | J88: 1121 | K88: 1121 | L88: Ленинградский вокзал → через площадь на Казанский (5 мин) → электричка + такси (12:54 → 15:15) | M88: ~15:30 | N88: 28.10 04:50 МСК → 28.10 15:30 МСК | O88: 10 ч 40 мин | Q88: https://www.tutu.ru/poezda/rasp_d.php?date=28.10.2026&nnst1=2004000&nnst2=2000000 | R88: Самый дешёвый, но подъём ~04:00 | S88: проверить
A89: Санкт-Петербург | B89: 1 | C89: Туда | D89: Удобный | E89: Сапсан | F89: 759А | G89: 28.10 09:00 | H89: 28.10 13:15 | I89: Москва, Ленинградский | J89: 4424 | K89: 4424 | L89: Ленинградский вокзал → через площадь на Казанский (5 мин) → электричка + такси (РЭКС 13:35 → 15:22) | M89: ~15:40 | N89: 28.10 08:15 МСК → 28.10 15:40 МСК | O89: 7 ч 25 мин | Q89: https://www.tutu.ru/poezda/rasp_d.php?date=28.10.2026&nnst1=2004000&nnst2=2000000 | R89: Днём, 4 ч; к экскурсии почти успевает | S89: проверить
A90: Санкт-Петербург | B90: 1 | C90: Обратно | D90: Самый дешёвый | E90: Поезд «Аврора», сидячий | F90: 750У | G90: 30.10 22:30 | H90: 31.10 05:00 | I90: СПб, Московский вокзал | J90: 2185 | K90: 2185 | L90: Электричка 18:43 → Казанский 20:47 → Ленинградский | N90: 30.10 18:15 МСК → 31.10 05:45 МСК | O90: 11 ч 30 мин | Q90: https://www.tutu.ru/poezda/rasp_d.php?date=30.10.2026&nnst1=2000000&nnst2=2004000 | R90: Ночь сидя
A91: Санкт-Петербург | B91: 1 | C91: Обратно | D91: Удобный | E91: Поезд «Аврора», сидячий | F91: 744У | G91: 31.10 13:50 | H91: 31.10 19:15 | I91: СПб, Московский вокзал | J91: 2130 | K91: 2130 | L91: 31.10 утро: электричка до Казанского → Ленинградский | N91: 31.10 10:30 МСК → 31.10 20:00 МСК | O91: 9 ч 30 мин | P91: +1 ночь 30→31 | Q91: https://www.tutu.ru/poezda/rasp_d.php?date=31.10.2026&nnst1=2000000&nnst2=2004000 | R91: Днём. Или Сапсан 768А 13:30 → 17:30, 4 666 ₽
A92: Нижний Новгород | B92: 1 | C92: Туда | D92: Самый дешёвый = Удобный | E92: Поезд «Буревестник», сидячий | F92: 705Э | G92: 28.10 07:20 | H92: 28.10 11:34 | I92: Москва, Восточный | J92: 2136 | K92: 2136 | L92: Восточный вокзал → МЦД/метро до Казанского (~30 мин) → электричка + такси (12:54 → 15:15) | M92: ~15:30 | N92: 28.10 06:35 МСК → 28.10 15:30 МСК | O92: 8 ч 55 мин | Q92: https://www.tutu.ru/poezda/rasp_d.php?date=28.10.2026&nnst1=2060000&nnst2=2000000 | R92: Основной вариант — машина с заездом во Владимир (лист «Авто») | S92: проверить
A93: Нижний Новгород | B93: 1 | C93: Обратно | D93: Самый дешёвый | E93: Ласточка, сидячий | F93: 723Я | G93: 30.10 21:15 | H93: 31.10 01:15 | I93: Нижний Новгород | J93: 2347 | K93: 2347 | L93: Электричка 18:43 → Казанский 20:47 → Восточный | N93: 30.10 18:15 МСК → 31.10 02:00 МСК | O93: 7 ч 45 мин | Q93: https://www.tutu.ru/poezda/rasp_d.php?date=30.10.2026&nnst1=2000000&nnst2=2060000 | R93: Дома глубокой ночью
A94: Нижний Новгород | B94: 1 | C94: Обратно | D94: Удобный | E94: Поезд «Буревестник», сидячий | F94: 703Х | G94: 31.10 13:45 | H94: 31.10 17:46 | I94: Нижний Новгород | J94: 2985 | K94: 2985 | L94: 31.10: электричка до Казанского → МЦД до Восточного | N94: 31.10 10:45 МСК → 31.10 18:30 МСК | O94: 7 ч 45 мин | P94: +1 ночь 30→31 | Q94: https://www.tutu.ru/poezda/rasp_d.php?date=31.10.2026&nnst1=2000000&nnst2=2060000 | R94: Днём
A95: Смоленск | B95: 1 | C95: Туда | D95: Самый дешёвый = Удобный | E95: Ласточка-премиум, сидячий | F95: 738М | G95: 28.10 07:29 | H95: 28.10 11:53 | I95: Москва, Белорусский | J95: 1832 | K95: 1832 | L95: Белорусский → метро до Комсомольской (~15 мин) → электричка + такси (12:54 → 15:15) | M95: ~15:30 | N95: 28.10 06:45 МСК → 28.10 15:30 МСК | O95: 8 ч 45 мин | Q95: https://www.tutu.ru/poezda/rasp_d.php?date=28.10.2026&nnst1=2000170&nnst2=2000000 | R95: К экскурсии в 16:00 успевает | S95: проверить
A96: Смоленск | B96: 1 | C96: Обратно | D96: Самый дешёвый | E96: Поезд, купе | F96: 027Б | G96: 30.10 23:30 | H96: 31.10 04:39 | I96: Смоленск | J96: 4022 | K96: 4022 | L96: Электричка 18:43 → Казанский → метро до Белорусской | N96: 30.10 18:15 МСК → 31.10 05:25 МСК | O96: 11 ч 10 мин | Q96: https://www.tutu.ru/poezda/rasp_d.php?date=30.10.2026&nnst1=2000000&nnst2=2000170 | R96: Дома ночью
A97: Смоленск | B97: 1 | C97: Обратно | D97: Удобный | E97: Ласточка, сидячий | F97: 733Х | G97: 31.10 09:54 | H97: 31.10 14:07 | I97: Смоленск | J97: 2595 | K97: 2595 | L97: 31.10 утро: электричка 07:22 → Казанский → метро | N97: 31.10 06:45 МСК → 31.10 14:50 МСК | O97: 8 ч 05 мин | P97: +1 ночь 30→31 | Q97: https://www.tutu.ru/poezda/rasp_d.php?date=31.10.2026&nnst1=2000000&nnst2=2000170 | R97: Днём. Или машина ~520 км
A98: Тверь | B98: 1 | C98: Туда | D98: Самый дешёвый | E98: Поезд «Аврора», сидячий | F98: 741У | G98: 28.10 10:16 | H98: 28.10 11:55 | I98: Москва, Ленинградский | J98: 695 | K98: 695 | L98: Ленинградский вокзал → через площадь на Казанский (5 мин) → электричка + такси (12:54 → 15:15) | M98: ~15:30 | N98: 28.10 09:30 МСК → 28.10 15:30 МСК | O98: 6 ч 00 мин | Q98: https://www.tutu.ru/poezda/rasp_d.php?date=28.10.2026&nnst1=2004600&nnst2=2000000 | S98: проверить
A99: Тверь | B99: 1 | C99: Туда | D99: Удобный | E99: Своя машина | G99: 28.10 ~09:30 | H99: 28.10 ~13:30 | I99: Коломна | J99: 1885 | K99: 1885 | L99: ~290 км через ЦКАД, ~4 ч | M99: ~13:30 | N99: 28.10 09:30 МСК → 28.10 13:30 МСК | O99: 4 ч 00 мин | R99: Топливо ~3 770 ₽ туда-обратно на машину
A100: Тверь | B100: 1 | C100: Обратно | D100: Самый дешёвый | E100: Поезд «Аврора», сидячий | F100: 750У | G100: 30.10 22:30 | H100: 31.10 ~00:05 | I100: Тверь | J100: 1000 | K100: 1000 | L100: Электричка 18:43 → Казанский 20:47 → Ленинградский | N100: 30.10 18:15 МСК → 31.10 00:50 МСК | O100: 6 ч 35 мин | Q100: https://www.tutu.ru/poezda/rasp_d.php?date=30.10.2026&nnst1=2000000&nnst2=2004600 | R100: Цена ориентировочная
...

Sheet Авто
A1: Экипаж | B1: Кто едет | C1: Чел. | D1: Маршрут | E1: Км до Коломны (в одну сторону) | F1: Время в пути | G1: Топливо туда-обратно, ₽ | H1: Платные дороги туда-обратно, ₽ | I1: Итого на машину, ₽ | J1: На 1 чел., ₽ | K1: Выезд / приезд (эконом) | L1: Примечание
A2: Пенза | B2: Ирышков Е.А. | C2: 1 | D2: Пенза — М-5 — Шацк — Рязань — Коломна | E2: 560 | F2: ~7 ч 30 мин | G2: =E2*2*'Правила и допущения'!$B$4/100*'Правила и допущения'!$B$5 | H2: 0 | I2: =G2+H2 | J2: =I2/C2 | K2: 27.10 выезд ~13:00 → 20:30; или 28.10 06:30 → 14:00 | L2: Близко к лимиту 600 км. Совместно с Саранском — только при встрече на М-5 (р-н Шацка), заезд в Саранск даёт ~630 км
A3: Саранск | B3: Ильин Д.С. | C3: 1 | D3: Саранск — Краснослободск — М-5 — Рязань — Коломна | E3: 500 | F3: ~7 ч | G3: =E3*2*'Правила и допущения'!$B$4/100*'Правила и допущения'!$B$5 | H3: 0 | I3: =G3+H3 | J3: =I3/C3 | K3: 28.10 выезд 07:00 → 14:00 | L3: Альтернатива — поезд 041Й (лист «Маршруты»)
A4: Тамбов | B4: Горелкин Д.Е. | C4: 1 | D4: Тамбов — Р-22 — Рязань — Коломна | E4: 390 | F4: ~5 ч | G4: =E4*2*'Правила и допущения'!$B$4/100*'Правила и допущения'!$B$5 | H4: 0 | I4: =G4+H4 | J4: =I4/C4 | K4: 28.10 выезд 09:00 → 14:00 | L4: Обратно 30.10 после 18:00 — дома ~23:30
A5: Липецк (3 чел.) | B5: Иванищева А.В., Кузнецов А.А., Зайцев С.А. | C5: 3 | D5: Липецк — Данков — Скопин — Рязань — Коломна | E5: 370 | F5: ~5 ч | G5: =E5*2*'Правила и допущения'!$B$4/100*'Правила и допущения'!$B$5 | H5: 0 | I5: =G5+H5 | J5: =I5/C5 | K5: 28.10 выезд 09:00 → 14:00 | L5: Одна машина на троих — самый выгодный вариант
A6: Воронеж (2 чел.) | B6: Летуновский В.М., Штанько О.М. | C6: 2 | D6: Воронеж — М-4 «Дон» — Кашира — Коломна | E6: 450 | F6: ~5 ч 30 мин | G6: =E6*2*'Правила и допущения'!$B$4/100*'Правила и допущения'!$B$5 | H6: 3600 | I6: =G6+H6 | J6: =I6/C6 | K6: 28.10 выезд 08:30 → 14:00 | L6: Платные участки М-4 — ориентир ~1 800 ₽ в одну сторону, проверить. Можно захватить 1 чел. из Липецка (+~40 км)
A7: Брянск + Орёл | B7: Бондарев С.А. (водитель), Мамонов С.В. | C7: 2 | D7: Брянск — Орёл — Тула — Венёв — Коломна | E7: 500 | F7: ~6 ч 30 мин | G7: =E7*2*'Правила и допущения'!$B$4/100*'Правила и допущения'!$B$5 | H7: 0 | I7: =G7+H7 | J7: =I7/C7 | K7: 28.10 выезд из Брянска 07:00, Орёл ~09:00 → 13:30 | L7: Орёл по пути, крюк не нужен. Если едут отдельно: Орёл → Коломна ~360 км, Брянск ~440 км (через Калугу)
A8: Н. Новгород + Владимир (3 чел.) | B8: Бабкин В.А., Меднов В.А. (из Н. Новгорода), Шабанов Р.В. (забрать во Владимире) | C8: 3 | D8: Н. Новгород — М-12 — Владимир — Петушки — Покров — Орехово-Зуево — Егорьевск — Коломна | E8: 430 | F8: ~6 ч | G8: =E8*2*'Правила и допущения'!$B$4/100*'Правила и допущения'!$B$5 | H8: 3000 | I8: =G8+H8 | J8: =I8/C8 | K8: 28.10 выезд из Н. Новгорода 08:00 → Владимир ~10:30 (забрать Шабанова) → Коломна ~14:00 | L8: Владимир по пути — крюк не нужен. М-12 платная, ~1 500 ₽ в одну сторону (ориентир); по бесплатной М-7 +~40 мин. Обратно 30.10 после 18:00: Владимир ~21:30, Н. Новгород ~00:30 — для водителя лучше 31.10 утром
A9: Калуга | B9: Макеев С.И. | C9: 1 | D9: Калуга — Таруса — Серпухов — Ступино — Коломна | E9: 230 | F9: ~3 ч 30 мин | G9: =E9*2*'Правила и допущения'!$B$4/100*'Правила и допущения'!$B$5 | H9: 0 | I9: =G9+H9 | J9: =I9/C9 | K9: 28.10 выезд 10:30 → 14:00 | L9: Если своей машины нет — поезд до Киевского вокзала (лист «Маршруты»)
A11: Расстояния и время — ориентир; точный маршрут и пробки проверить в Яндекс Картах. Обратно: эконом — выезд 30.10 в 18:15; удобный — 31.10 утром + доп. ночь.

Sheet Группы такси
A1: Дата / аэропорт | B1: Группа | C1: Кто (город, рейс, прилёт/вылет) | D1: Чел. | E1: Сбор / выезд | F1: Машин | G1: Цена на машину, ₽ | H1: На 1 чел., ₽ | I1: Комментарий
A2: 27.10 Шереметьево (удобный) | B2: Ш-0 | C2: Омск SU-1689 17:55 | D2: 1 | E2: сразу после прилёта | F2: 1 | G2: 5000 | H2: =G2*F2/D2 | I2: Или аэроэкспресс + электричка
A3: 28.10 Домодедово (удобный) | B3: Д-1 | C3: Новокузнецк S7-2626 10:00; Екатеринбург U6-272 10:10 — группа 9 чел. + Нижний Тагил; Чита U6-94 10:20 | D3: 12 | E3: сбор ~10:45 | F3: 2 | G3: 4000 | H3: =G3*F3/D3 | I3: 2 минивэна (заказать заранее)
A4: 28.10 Домодедово (удобный) | B4: Д-2 | C4: Ревда U6-300 12:40 | D4: 1 | E4: ~13:10 | F4: 1 | G4: 3000 | H4: =G4*F4/D4
A5: 28.10 Домодедово (удобный) | B5: Д-3 | C5: Уфа S7-1136 16:15; Ижевск S7-1166 20:05 | D5: 1 | E5: по прилёту | F5: 1 | G5: 3000 | H5: =G5*F5/D5 | I5: Прилёты далеко по времени — отдельные такси
A6: 28.10 Шереметьево (удобный) | B6: Ш-1 | C6: Новосибирск SU-1307 10:45 (3 чел.); Абакан SU-1479 11:00; Чебоксары DP-6808 11:45; Улан-Удэ SU-1455 11:45; Казань N4-60 11:55 | D6: 7 | E6: сбор ~12:15 | F6: 1 | G6: 7000 | H6: =G6*F6/D6 | I6: Минивэн на 7–8 мест
A7: 28.10 Шереметьево (удобный) | B7: Ш-2 | C7: Волгоград DP-6966 12:10; Красноярск SU-1483 12:20; Иркутск SU-6732 12:25 (5 чел.) | D7: 7 | E7: сбор ~12:50 | F7: 1 | G7: 7000 | H7: =G7*F7/D7 | I7: Минивэн
A8: 28.10 Шереметьево (удобный) | B8: Ш-3 | C8: Астрахань DP-6962 13:45 | D8: 1 | E8: ~14:15 | F8: 1 | G8: 5000 | H8: =G8*F8/D8 | I8: Или аэроэкспресс + электричка
A9: 28.10 Шереметьево (удобный) | B9: Ш-4 | C9: Челябинск SU-1421 17:10; Саратов DP-6864 18:20 (2 чел.); Наб. Челны DP-6846 18:30; Оренбург N4-78 18:55 | D9: 5 | E9: сбор ~19:15 | F9: 1 | G9: 7000 | H9: =G9*F9/D9 | I9: Минивэн; в гостинице ~22:30
A10: 28.10 Внуково (удобный) | B10: В-1 | C10: Ульяновск DP-466 11:50 (2 чел.); Магнитогорск A4-7062 13:00 | D10: 3 | E10: сбор ~13:20 | F10: 1 | G10: 4500 | H10: =G10*F10/D10
A11: 28.10 Внуково (удобный) | B11: В-2 | C11: Самара DP-422 15:45; Тюмень UT-464 18:55 | D11: 1 | E11: по прилёту | F11: 1 | G11: 4500 | H11: =G11*F11/D11 | I11: Отдельные такси
A12: 31.10 → Домодедово (удобный) | B12: О-1 | C12: Екатеринбург + Нижний Тагил U6-261 10:00 (10 чел.); Ревда U6-261 | D12: 11 | E12: выезд ~07:00 | F12: 2 | G12: 4000 | H12: =G12*F12/D12 | I12: 2 минивэна
A13: 31.10 → Домодедово (удобный) | B13: О-2 | C13: Уфа S7-1135 11:00; Иркутск S7-3021 12:05 (5 чел.) | D13: 6 | E13: выезд ~08:30 | F13: 1 | G13: 4000 | H13: =G13*F13/D13 | I13: Минивэн
A14: 31.10 → Домодедово (удобный) | B14: О-3 | C14: Ижевск S7-1165 15:10; Чита U6-93 19:40 | D14: 1 | E14: по времени рейсов | F14: 1 | G14: 3000 | H14: =G14*F14/D14 | I14: Отдельные такси
A15: 31.10 → Шереметьево (удобный) | B15: О-4 | C15: Челябинск SU-1420 10:50; Магнитогорск SU-1420 10:50 | D15: 2 | E15: выезд ~06:15 | F15: 1 | G15: 5000 | H15: =G15*F15/D15
A16: 31.10 → Шереметьево (удобный) | B16: О-5 | C16: Новосибирск SU-1076 12:20 (3 чел.); Красноярск SU-1488 13:05 | D16: 4 | E16: выезд ~07:45 | F16: 1 | G16: 5000 | H16: =G16*F16/D16
A17: 31.10 → Шереметьево (удобный) | B17: О-6 | C17: Астрахань DP-6963 13:50; Наб. Челны DP-6845 14:10; Самара DP-6581 14:15; Оренбург SU-1248 15:30 | D17: 4 | E17: выезд ~09:15 | F17: 1 | G17: 5000 | H17: =G17*F17/D17 | I17: Или электричка + аэроэкспресс
A18: 31.10 → Шереметьево (удобный) | B18: О-7 | C18: Казань DP-6843 17:30; Волгоград DP-6969 18:35; Чебоксары DP-6815 19:30 | D18: 3 | E18: выезд ~13:00 | F18: 1 | G18: 5000 | H18: =G18*F18/D18
A19: 31.10 → Шереметьево (удобный) | B19: О-8 | C19: Улан-Удэ SU-1454 21:55; Омск DP-6523 22:00; Новокузнецк SU-1458 22:35; Абакан SU-1478 23:55 | D19: 4 | E19: выезд ~17:00 | F19: 1 | G19: 5000 | H19: =G19*F19/D19 | I19: Вечерние рейсы в Сибирь
A20: 31.10 → Внуково (удобный) | B20: О-9 | C20: Тюмень UT-463 10:00 | D20: 1 | E20: выезд ~06:45 | F20: 1 | G20: 4500 | H20: =G20*F20/D20
A21: 31.10 → Внуково (удобный) | B21: О-10 | C21: Саратов DP-475 17:55 (2 чел.); Ульяновск DP-485 19:35 (2 чел.) | D21: 4 | E21: выезд ~13:30 | F21: 1 | G21: 4500 | H21: =G21*F21/D21
A22: 30.10 → аэропорты (эконом) | B22: Э-1 | C22: Домодедово: Новокузнецк S7-2625 23:35; Улан-Удэ S7-3033 22:20; Ревда/Уфа U6-271/—. Внуково: Уфа DP-435 23:40; Екатеринбург DP-403 23:50 (10 чел.); Челябинск DP-413 23:45. Шереметьево: Омск DP-6521 23:45; Тюмень DP-6561 23:50; Магнитогорск SU-1428 00:40 | D22: 20 | E22: выезд 18:15 | F22: 4 | G22: 6000 | H22: =G22*F22/D22 | I22: Эконом-вариант: ночные рейсы сразу после конференции

Sheet Как добраться до гостиницы
A1: Гостиница «Коломна»: пл. Советская, 2, Коломна. Тел. +7 (496) 612-18-96. Заезд с 14:00.
A3: Откуда | B3: Как ехать | C3: Время (с пробками) | D3: Стоимость | E3: Совет
A4: Аэропорт Домодедово | B4: Такси напрямую (~95 км, М-4 / Каширское ш.) | C4: 1 ч 45 мин (ср днём) + 40 мин на выход с багажом | D4: 2 500–4 500 ₽ за машину | E4: Лучший вариант, особенно группой 2–4 чел.
A5: Аэропорт Шереметьево | B5: Аэроэкспресс → Белорусский вокзал (~40 мин) → метро до Комсомольской (~20 мин) → электричка с Казанского до ст. Коломна → такси 10 мин | C5: ~4 ч | D5: 700 ₽ (650 ₽ при покупке заранее; «Вместе» 2 400 ₽ на 4 чел.) + 490–620 ₽ + ~300 ₽ | E5: Дёшево; зависит от расписания электричек
A6: Аэропорт Шереметьево | B6: Такси напрямую (~150 км) | C6: ~3 ч + 40 мин | D6: 4 200–5 800 ₽ за машину | E6: Выгодно для 3–4 чел.
A7: Аэропорт Внуково | B7: Метро (ст. «Аэропорт Внуково») → Комсомольская → электричка с Казанского → такси. Аэроэкспресса больше нет | C7: ~3 ч 30 мин | D7: ~90 ₽ + 490–620 ₽ + ~300 ₽
A8: Аэропорт Внуково | B8: Такси напрямую (~140 км) | C8: ~2 ч 45 мин + 40 мин | D8: 4 100–5 500 ₽ за машину
A9: Казанский вокзал | B9: Электричка до ст. «Коломна» (не Голутвин — ближе к гостинице), затем такси | C9: 1 ч 40 мин – 2 ч 25 мин (РЭКС ~1 ч 45 мин) | D9: «Стандарт плюс» 490 ₽, РЭКС 620 ₽; такси ~300 ₽ | E9: «Ласточек» до Коломны в продаже нет
A10: Павелецкий / Курский / Киевский / Восточный | B10: Метро или МЦД до Комсомольской (Казанский вокзал), дальше как выше | C10: +20–30 мин | D10: ~90 ₽ | E10: Закладывать не меньше 40 мин на пересадку
A11: Станция Голутвин | B11: Такси до гостиницы | C11: ~15 мин | D11: ~350 ₽ | E11: Сюда приходят поезда дальнего следования (напр. 213*С из Воронежа в 04:50)
A14: Электрички Казанский вокзал → Коломна, 28.10 (ср) | C14: Коломна → Казанский вокзал, 30.10 (пт)
A15: 07:22 → 09:15 | C15: 18:43 → 20:47
A16: 08:47 → 10:28 (РЭКС) | C16: 19:43 → 22:10
A17: 09:48 → 11:36 | C17: 20:10 → 22:30
A18: перерыв до 12:54 | C18: 21:01 → 22:38 (РЭКС)
A19: 12:54 → 15:15 | C19: 21:41 → 00:01
A20: 13:35 → 15:22 (РЭКС)
A22: Расписание электричек: https://www.tutu.ru/prigorod/ (Москва Казанская — Коломна). Проверка пробок: Яндекс Карты или 2ГИС → «Время и дата отправления».

Sheet Правила и допущения
A1: Параметры расчёта (можно менять — итоги пересчитаются)
A3: Доп. ночь в гостинице «Коломна», ₽ | B3: 4000 | C3: Номер от ~3 050 ₽; уточнить корпоративный тариф: +7 (496) 612-18-96
A4: Расход топлива, л/100 км | B4: 10 | C4: Средний легковой автомобиль
A5: Цена бензина, ₽/л | B5: 65 | C5: АИ-95, октябрь 2026 — ориентир
A7: Правила подбора маршрутов
A8: Ключевые даты | B8: Экскурсия 28.10 в 16:00 (заселиться к 15:00). Если к 15:00 не успеть — приехать так, чтобы к 9:00 29.10 выспаться. Окончание конференции 30.10 в 18:00.
A9: Гостиница | B9: «Коломна», пл. Советская, 2. Заезд с 14:00. Тел. +7 (496) 612-18-96. При раннем приезде (поезд в 05–07 ч) — камера хранения или ранний заезд, договориться заранее.
A10: Два варианта | B10: «Самый дешёвый» — минимальная цена (ранние вылеты, ночные рейсы, ночные поезда допускаются). «Удобный» — без подъёма среди ночи и без ночи в дороге. Если самый дешёвый вариант и есть удобный — показан один (пометка «Самый дешёвый = Удобный»).
A11: Критерии удобного варианта | B11: Туда: вылет/отправление не раньше ~09:00 (подъём не раньше 5:30–6:00); приезд в Коломну до 22–23 ч 28.10 (экскурсию можно пропустить) или днём накануне с ночёвкой. Обратно: не ночным рейсом сразу после конференции, а 31.10 днём после ночи в гостинице (+1 ночь). Вылеты в 23:00–00:40 и ночные поезда отнесены к эконому.
A12: Где удобного обратного рейса нет | B12: Омск, Абакан, Новокузнецк, Улан-Удэ, Чита: из Москвы летают только вечером/ночью (разница во времени 3–6 ч). В удобном варианте — вечерний рейс 31.10 после дня отдыха. Магнитогорск: прямые только 00:40 и 07:40 — удобный через Челябинск + автобус. Донецк: ночной переезд неизбежен, удобный — в купе.
A13: Самолёты | B13: Только эконом. Две цены: без багажа (только ручная кладь) и с багажом. Цены — обычные, за один билет (групповых тарифов и скидок нет), на 28.09.2026, быстро меняются. Когда на один рейс летят несколько человек, билеты лучше купить заранее и сразу.
A14: Аэропорт | B14: В аэропорту минимум за 2 часа до вылета (Москва и крупные города); в небольших городах — за 1,5 часа. Учитывать время подъёма и дорогу до аэропорта: рейсы с вылетом до ~07:00 означают подъём среди ночи.
A15: Пробки | B15: Время такси заложено с учётом пробок: среда 28.10 днём (DME→Коломна 1 ч 45 мин, SVO ~3 ч, VKO ~2 ч 45 мин + 40 мин на выход с багажом); пятница 30.10 вечером, выезд 18:15: DME ~2 ч, VKO ~3 ч, SVO ~3 ч 30 мин; суббота 31.10 утром: DME 1 ч 30 мин, VKO 2 ч 15 мин, SVO 2 ч 30 мин.
A16: Вечерний вылет 30.10 возможен, если | B16: Домодедово — вылет не раньше ~22:15; Внуково — ~23:15; Шереметьево — ~23:45. Иначе — 31.10 + доп. ночь.
A17: Поезда | B17: Только купе или сидячие, без плацкарта. Не более суток в пути. Идеал — вечером сел, днём в Коломне.
A18: Машина | B18: Для городов до 600 км. Совместные поездки предложены, если по пути. Для водителей после конференции безопаснее выезд 31.10 утром (+ ночь).
A19: Проверка пробок | B19: Яндекс Карты или 2ГИС: построить маршрут → «Время и дата отправления» → выбрать 28.10 и нужный час. Покажут прогноз по статистике пробок.
... A21: Что проверить | B21: Строки с пометкой «проверить» посчитаны по расписанию соседнего дня. Донецк: автобусы из ДНР продаются у перевозчиков, не на Туту; многие ходят через день — уточнить дату.
